{"data":[{"symbol":"INDIAMART","buyOrderPrice1":10,"buyOrderQty1":700,"sellOrderPrice1":100,"sellQty1":19,"lastTradedPrice":0,"underLyingLtp":4076.65,"futuresLtp":4032.45,"spread":44.2,"spreadPer":1.08,"openPositions":0,"annualisedYieldPer":0,"volume":0,"turnOver":0,"transactionValue":0,"caExpDate":"10-May-2022","ca":"BUY BACK 10-May-2022","meta":{"isSLBSec":true}},{"symbol":"COLPAL","buyOrderPrice1":0,"buyOrderQty1":0,"sellOrderPrice1":0,"sellQty1":0,"lastTradedPrice":0,"underLyingLtp":1544.9,"futuresLtp":1537,"spread":7.9,"spreadPer":0.51,"openPositions":0,"annualisedYieldPer":0,"volume":0,"turnOver":0,"transactionValue":0,"caExpDate":"20-Jul-2022","ca":"ANNUAL GENERAL MEETING 20-Jul-2022","meta":{"isSLBSec":true}},{"symbol":"UBL","buyOrderPrice1":0,"buyOrderQty1":0,"sellOrderPrice1":0,"sellQty1":0,"lastTradedPrice":0,"underLyingLtp":1626.25,"futuresLtp":1619.25,"spread":7,"spreadPer":0.43,"openPositions":0,"annualisedYieldPer":0,"volume":0,"turnOver":0,"transactionValue":0,"caExpDate":"02-Aug-2022","ca":"ANNUAL GENERAL MEETING/DIVIDEND - RS 10.50 PER SH 02-Aug-2022","meta":{"isSLBSec":true}},{"symbol":"COFORGE","buyOrderPrice1":41,"buyOrderQty1":240,"sellOrderPrice1":59.95,"sellQty1":50,"lastTradedPrice":0,"underLyingLtp":3769.35,"futuresLtp":3755.8,"spread":13.55,"spreadPer":0.36,"openPositions":0,"annualisedYieldPer":60.52104474246222,"volume":0,"turnOver":0,"transactionValue":0,"caExpDate":"23-May-2022","ca":"INTERIM DIVIDEND - RS  13 PER SHARE 23-May-2022","meta":{"isSLBSec":true}},{"symbol":"NAUKRI","buyOrderPrice1":0,"buyOrderQty1":0,"sellOrderPrice1":20,"sellQty1":296,"lastTradedPrice":0,"underLyingLtp":3867.8,"futuresLtp":3857.4,"spread":10.4,"spreadPer":0.27,"openPositions":0,"annualisedYieldPer":0,"volume":0,"turnOver":0,"transactionValue":0,"caExpDate":"18-Aug-2022","ca":"ANNUAL GENERAL MEETING/DIVIDEND - RS 5 PER SHARE 18-Aug-2022","meta":{"isSLBSec":true}},{"symbol":"ITC","buyOrderPrice1":0,"buyOrderQty1":0,"sellOrderPrice1":0.2,"sellQty1":3561,"lastTradedPrice":0,"underLyingLtp":304.2,"futuresLtp":303.4,"spread":0.8,"spreadPer":0.26,"openPositions":0,"annualisedYieldPer":1.4998356344510193,"volume":0,"turnOver":0,"transactionValue":0,"caExpDate":"26-May-2022","ca":"DIVIDEND - RS 6.25 PER SHARE 26-May-2022","meta":{"isSLBSec":true}},{"symbol":"GUJGASLTD","buyOrderPrice1":2.5,"buyOrderQty1":30000,"sellOrderPrice1":4.5,"sellQty1":2000,"lastTradedPrice":0,"underLyingLtp":450.25,"futuresLtp":449.25,"spread":1,"spreadPer":0.22,"openPositions":0,"annualisedYieldPer":40.53303720155469,"volume":0,"turnOver":0,"transactionValue":0,"caExpDate":"08-Sep-2021","ca":" DIVIDEND - RS 2 PER SHARE 08-Sep-2021","meta":{"isSLBSec":true}},{"symbol":"AXISBANK","buyOrderPrice1":0,"buyOrderQty1":0,"sellOrderPrice1":0,"sellQty1":0,"lastTradedPrice":0,"underLyingLtp":719.5,"futuresLtp":718.1,"spread":1.4,"spreadPer":0.19,"openPositions":0,"annualisedYieldPer":0,"volume":0,"turnOver":0,"transactionValue":0,"caExpDate":"07-Jul-2022","ca":"DIVIDEND - RS 1 PER SHARE 07-Jul-2022","meta":{"isSLBSec":true}},{"symbol":"GAIL","buyOrderPrice1":0,"buyOrderQty1":0,"sellOrderPrice1":0.5,"sellQty1":1856,"lastTradedPrice":0,"underLyingLtp":145.85,"futuresLtp":145.6,"spread":0.25,"spreadPer":0.17,"openPositions":0,"annualisedYieldPer":0,"volume":0,"turnOver":0,"transactionValue":0,"caExpDate":"01-Aug-2022","ca":"DIVIDEND - RS 1 PER SHARE 01-Aug-2022","meta":{"isSLBSec":true}},{"symbol":"CANFINHOME","buyOrderPrice1":0,"buyOrderQty1":0,"sellOrderPrice1":0,"sellQty1":0,"lastTradedPrice":0,"underLyingLtp":559.3,"futuresLtp":558.4,"spread":0.9,"spreadPer":0.16,"openPositions":0,"annualisedYieldPer":0,"volume":0,"turnOver":0,"transactionValue":0,"caExpDate":"23-Dec-2021","ca":" INTERIM DIVIDEND - RS 1.50 PER SHARE 23-Dec-2021","meta":{"isSLBSec":true}},{"symbol":"FEDERALBNK","buyOrderPrice1":0,"buyOrderQty1":0,"sellOrderPrice1":0,"sellQty1":0,"lastTradedPrice":0,"underLyingLtp":107.1,"futuresLtp":106.95,"spread":0.15,"spreadPer":0.14,"openPositions":0,"annualisedYieldPer":0,"volume":0,"turnOver":0,"transactionValue":0,"caExpDate":"19-Jul-2022","ca":"ANNUAL GENERAL MEETING/DIVIDEND - RS  1.80 PER SHARE 19-Jul-2022","meta":{"isSLBSec":true}},{"symbol":"L&TFH","buyOrderPrice1":0,"buyOrderQty1":0,"sellOrderPrice1":0,"sellQty1":0,"lastTradedPrice":0,"underLyingLtp":72.45,"futuresLtp":72.35,"spread":0.1,"spreadPer":0.14,"openPositions":0,"annualisedYieldPer":0,"volume":0,"turnOver":0,"transactionValue":0,"caExpDate":"01-Jul-2022","ca":"DIVIDEND - RS 0.50 PER SHARE 01-Jul-2022","meta":{"isSLBSec":true}},{"symbol":"OFSS","buyOrderPrice1":0,"buyOrderQty1":0,"sellOrderPrice1":10,"sellQty1":2,"lastTradedPrice":0,"underLyingLtp":3048.9,"futuresLtp":3045,"spread":3.9,"spreadPer":0.13,"openPositions":0,"annualisedYieldPer":0,"volume":0,"turnOver":0,"transactionValue":0,"caExpDate":"26-Jul-2022","ca":"ANNUAL GENERAL MEETING 26-Jul-2022","meta":{"isSLBSec":true}},{"symbol":"RECLTD","buyOrderPrice1":0,"buyOrderQty1":0,"sellOrderPrice1":0.5,"sellQty1":100000,"lastTradedPrice":0,"underLyingLtp":128.6,"futuresLtp":128.45,"spread":0.15,"spreadPer":0.12,"openPositions":0,"annualisedYieldPer":8.869556765163297,"volume":0,"turnOver":0,"transactionValue":0,"caExpDate":"12-Jul-2022","ca":"DIVIDEND - RS 4.80 PER SHARE 12-Jul-2022","meta":{"isSLBSec":true}},{"symbol":"CIPLA","buyOrderPrice1":0,"buyOrderQty1":0,"sellOrderPrice1":0.5,"sellQty1":200,"lastTradedPrice":0,"underLyingLtp":972.4,"futuresLtp":971.35,"spread":1.05,"spreadPer":0.11,"openPositions":0,"annualisedYieldPer":0,"volume":0,"turnOver":0,"transactionValue":0,"caExpDate":"09-Aug-2021","ca":" ANNUAL GENERAL MEETING/DIVIDEND - RS 5 PER SHARE 09-Aug-2021","meta":{"isSLBSec":true}},{"symbol":"ESCORTS","buyOrderPrice1":0,"buyOrderQty1":0,"sellOrderPrice1":0,"sellQty1":0,"lastTradedPrice":0,"underLyingLtp":1696.75,"futuresLtp":1695.05,"spread":1.7,"spreadPer":0.1,"openPositions":0,"annualisedYieldPer":0,"volume":0,"turnOver":0,"transactionValue":0,"caExpDate":"30-Jun-2022","ca":"ANNUAL GENERAL MEETING/DIVIDEND - RS 7 PER SHARE 30-Jun-2022","meta":{"isSLBSec":true}},{"symbol":"M&MFIN","buyOrderPrice1":0,"buyOrderQty1":0,"sellOrderPrice1":0,"sellQty1":0,"lastTradedPrice":0,"underLyingLtp":198.4,"futuresLtp":198.2,"spread":0.2,"spreadPer":0.1,"openPositions":0,"annualisedYieldPer":0,"volume":0,"turnOver":0,"transactionValue":0,"caExpDate":"20-Jul-2022","ca":"ANNUAL GENERAL MEETING/DIVIDEND - RS 3.60 PER SHARE 20-Jul-2022","meta":{"isSLBSec":true}},{"symbol":"COALINDIA","buyOrderPrice1":0,"buyOrderQty1":0,"sellOrderPrice1":0.5,"sellQty1":120800,"lastTradedPrice":0,"underLyingLtp":203.75,"futuresLtp":203.55,"spread":0.2,"spreadPer":0.1,"openPositions":0,"annualisedYieldPer":11.196319018404909,"volume":0,"turnOver":0,"transactionValue":0,"caExpDate":"21-Feb-2022","ca":"INTERIM DIVIDEND - RS 5 PER SHARE 21-Feb-2022","meta":{"isSLBSec":true}},{"symbol":"TVSMOTOR","buyOrderPrice1":1,"buyOrderQty1":28000,"sellOrderPrice1":2.99,"sellQty1":1000,"lastTradedPrice":0,"underLyingLtp":845.8,"futuresLtp":845,"spread":0.8,"spreadPer":0.09,"openPositions":0,"annualisedYieldPer":21.577205013005436,"volume":0,"turnOver":0,"transactionValue":0,"caExpDate":"25-Mar-2022","ca":"INTERIM DIVIDEND - RS 3.75 PER SHARE 25-Mar-2022","meta":{"isSLBSec":true}},{"symbol":"INFY","buyOrderPrice1":0,"buyOrderQty1":0,"sellOrderPrice1":0.45,"sellQty1":1570,"lastTradedPrice":0,"underLyingLtp":1466.5,"futuresLtp":1465.35,"spread":1.15,"spreadPer":0.08,"openPositions":0,"annualisedYieldPer":1.5555744971019434,"volume":0,"turnOver":0,"transactionValue":0,"caExpDate":"31-May-2022","ca":"ANNUAL GENERAL MEETING/DIVIDEND - RS 16 PER SHARE 31-May-2022","meta":{"isSLBSec":true}},{"symbol":"BHARTIARTL","buyOrderPrice1":0,"buyOrderQty1":0,"sellOrderPrice1":0.5,"sellQty1":100,"lastTradedPrice":0,"underLyingLtp":675,"futuresLtp":674.55,"spread":0.45,"spreadPer":0.07,"openPositions":0,"annualisedYieldPer":0,"volume":0,"turnOver":0,"transactionValue":0,"caExpDate":"01-Aug-2022","ca":"DIVIDEND - RS 3 PER SHARE 01-Aug-2022","meta":{"isSLBSec":true}},{"symbol":"SBIN","buyOrderPrice1":0,"buyOrderQty1":0,"sellOrderPrice1":0,"sellQty1":0,"lastTradedPrice":0,"underLyingLtp":522.9,"futuresLtp":522.6,"spread":0.3,"spreadPer":0.06,"openPositions":0,"annualisedYieldPer":0,"volume":0,"turnOver":0,"transactionValue":0,"caExpDate":"25-May-2022","ca":"DIVIDEND - RS 7.10 PER SHARE 25-May-2022","meta":{"isSLBSec":true}},{"symbol":"ASIANPAINT","buyOrderPrice1":0,"buyOrderQty1":0,"sellOrderPrice1":0.49,"sellQty1":1110,"lastTradedPrice":0,"underLyingLtp":3152.8,"futuresLtp":3150.85,"spread":1.95,"spreadPer":0.06,"openPositions":0,"annualisedYieldPer":0.7235631819335193,"volume":0,"turnOver":0,"transactionValue":0,"caExpDate":"09-Jun-2022","ca":"DIVIDEND - RS 15.50 PER SHARE 09-Jun-2022","meta":{"isSLBSec":true}},{"symbol":"BPCL","buyOrderPrice1":0,"buyOrderQty1":0,"sellOrderPrice1":0,"sellQty1":0,"lastTradedPrice":0,"underLyingLtp":323.15,"futuresLtp":323,"spread":0.15,"spreadPer":0.05,"openPositions":0,"annualisedYieldPer":0,"volume":0,"turnOver":0,"transactionValue":0,"caExpDate":"10-Feb-2022","ca":"INTERIM DIVIDEND - RS 5 PER SHARE 10-Feb-2022","meta":{"isSLBSec":true}},{"symbol":"BATAINDIA","buyOrderPrice1":0,"buyOrderQty1":0,"sellOrderPrice1":0,"sellQty1":0,"lastTradedPrice":0,"underLyingLtp":1819.35,"futuresLtp":1818.5,"spread":0.85,"spreadPer":0.05,"openPositions":0,"annualisedYieldPer":0,"volume":0,"turnOver":0,"transactionValue":0,"caExpDate":"04-Aug-2022","ca":"ANNUAL GENERAL MEETING/DIVIDEND - RS 4 PER SHARE/SPECIAL DIVIDEND - RS 50.5 PER SHARE 04-Aug-2022","meta":{"isSLBSec":true}},{"symbol":"ADANIENT","buyOrderPrice1":0,"buyOrderQty1":0,"sellOrderPrice1":0,"sellQty1":0,"lastTradedPrice":0,"underLyingLtp":2546.15,"futuresLtp":2544.8,"spread":1.35,"spreadPer":0.05,"openPositions":0,"annualisedYieldPer":0,"volume":0,"turnOver":0,"transactionValue":0,"caExpDate":"14-Jul-2022","ca":"DIVIDEND - RE 1 PER SHARE 14-Jul-2022","meta":{"isSLBSec":true}},{"symbol":"POWERGRID","buyOrderPrice1":0,"buyOrderQty1":0,"sellOrderPrice1":0.45,"sellQty1":5,"lastTradedPrice":0,"underLyingLtp":210.55,"futuresLtp":210.45,"spread":0.1,"spreadPer":0.05,"openPositions":0,"annualisedYieldPer":0,"volume":0,"turnOver":0,"transactionValue":0,"caExpDate":"16-Feb-2022","ca":"INTERIM DIVIDEND - RS 5.50 PER SHARE 16-Feb-2022","meta":{"isSLBSec":true}},{"symbol":"PVR","buyOrderPrice1":0,"buyOrderQty1":0,"sellOrderPrice1":0,"sellQty1":0,"lastTradedPrice":0,"underLyingLtp":1988.95,"futuresLtp":1987.9,"spread":1.05,"spreadPer":0.05,"openPositions":0,"annualisedYieldPer":0,"volume":0,"turnOver":0,"transactionValue":0,"caExpDate":"09-Jul-2020","ca":" RIGHTS 7:94 @ PREMIUM RS 774/- 09-Jul-2020","meta":{"isSLBSec":true}},{"symbol":"LAURUSLABS","buyOrderPrice1":0,"buyOrderQty1":0,"sellOrderPrice1":0,"sellQty1":0,"lastTradedPrice":0,"underLyingLtp":495.65,"futuresLtp":495.45,"spread":0.2,"spreadPer":0.04,"openPositions":0,"annualisedYieldPer":0,"volume":0,"turnOver":0,"transactionValue":0,"caExpDate":"22-Jun-2022","ca":"ANNUAL GENERAL MEETING 22-Jun-2022","meta":{"isSLBSec":true}},{"symbol":"GSPL","buyOrderPrice1":0,"buyOrderQty1":0,"sellOrderPrice1":0,"sellQty1":0,"lastTradedPrice":0,"underLyingLtp":228.05,"futuresLtp":227.95,"spread":0.1,"spreadPer":0.04,"openPositions":0,"annualisedYieldPer":0,"volume":0,"turnOver":0,"transactionValue":0,"caExpDate":"08-Sep-2021","ca":" DIVIDEND - RS 2 PER SH 08-Sep-2021","meta":{"isSLBSec":true}},{"symbol":"INTELLECT","buyOrderPrice1":0,"buyOrderQty1":0,"sellOrderPrice1":0,"sellQty1":0,"lastTradedPrice":0,"underLyingLtp":650.45,"futuresLtp":650.2,"spread":0.25,"spreadPer":0.04,"openPositions":0,"annualisedYieldPer":0,"volume":0,"turnOver":0,"transactionValue":0,"caExpDate":"21-Jul-2022","ca":"DIVIDEND - RS 2.5 PER SHARE 21-Jul-2022","meta":{"isSLBSec":true}},{"symbol":"TCS","buyOrderPrice1":0,"buyOrderQty1":0,"sellOrderPrice1":1,"sellQty1":21,"lastTradedPrice":0,"underLyingLtp":3163.8,"futuresLtp":3162.4,"spread":1.4,"spreadPer":0.04,"openPositions":0,"annualisedYieldPer":0.7210474745559138,"volume":0,"turnOver":0,"transactionValue":0,"caExpDate":"14-Jul-2022","ca":"INTERIM DIVIDEND- RS 8 PER SHARE 14-Jul-2022","meta":{"isSLBSec":true}},{"symbol":"HAL","buyOrderPrice1":0,"buyOrderQty1":0,"sellOrderPrice1":15,"sellQty1":52,"lastTradedPrice":0,"underLyingLtp":1923,"futuresLtp":1922.15,"spread":0.85,"spreadPer":0.04,"openPositions":0,"annualisedYieldPer":0,"volume":0,"turnOver":0,"transactionValue":0,"caExpDate":"17-Feb-2022","ca":"INTERIM DIVIDEND - RS 26 PER SHARE 17-Feb-2022","meta":{"isSLBSec":true}},{"symbol":"INDUSTOWER","buyOrderPrice1":0,"buyOrderQty1":0,"sellOrderPrice1":0,"sellQty1":0,"lastTradedPrice":0,"underLyingLtp":223.85,"futuresLtp":223.75,"spread":0.1,"spreadPer":0.04,"openPositions":0,"annualisedYieldPer":0,"volume":0,"turnOver":0,"transactionValue":0,"caExpDate":"13-May-2022","ca":"INTERIM DIVIDEND - RS 11 PER SHARE 13-May-2022","meta":{"isSLBSec":true}},{"symbol":"HINDALCO","buyOrderPrice1":0,"buyOrderQty1":0,"sellOrderPrice1":0,"sellQty1":0,"lastTradedPrice":0,"underLyingLtp":387.1,"futuresLtp":387,"spread":0.1,"spreadPer":0.03,"openPositions":0,"annualisedYieldPer":0,"volume":0,"turnOver":0,"transactionValue":0,"caExpDate":"12-Aug-2021","ca":" ANNUAL GENERAL MEETING/DIVIDEND - RS 3 PER SHARE 12-Aug-2021","meta":{"isSLBSec":true}},{"symbol":"HDFC","buyOrderPrice1":0,"buyOrderQty1":0,"sellOrderPrice1":0.5,"sellQty1":1191,"lastTradedPrice":0,"underLyingLtp":2314.3,"futuresLtp":2313.6,"spread":0.7,"spreadPer":0.03,"openPositions":0,"annualisedYieldPer":1.9714384479108151,"volume":0,"turnOver":0,"transactionValue":0,"caExpDate":"31-May-2022","ca":"DIVIDEND - RS 30 PER SHARE 31-May-2022","meta":{"isSLBSec":true}},{"symbol":"NTPC","buyOrderPrice1":0,"buyOrderQty1":0,"sellOrderPrice1":0.45,"sellQty1":5199,"lastTradedPrice":0,"underLyingLtp":149.7,"futuresLtp":149.65,"spread":0.05,"spreadPer":0.03,"openPositions":0,"annualisedYieldPer":7.619405477621911,"volume":0,"turnOver":0,"transactionValue":0,"caExpDate":"03-Feb-2022","ca":"INTERIM DIVIDEND - RS 4 PER SHARE 03-Feb-2022","meta":{"isSLBSec":true}},{"symbol":"GRASIM","buyOrderPrice1":0,"buyOrderQty1":0,"sellOrderPrice1":2,"sellQty1":505,"lastTradedPrice":0,"underLyingLtp":1552.95,"futuresLtp":1552.45,"spread":0.5,"spreadPer":0.03,"openPositions":0,"annualisedYieldPer":0,"volume":0,"turnOver":0,"transactionValue":0,"caExpDate":"12-Aug-2021","ca":" ANNUAL GENERAL MEETING/DIVIDEND - RS 5  PER SHARE/ SPECIAL DIVIDEND - RS 4 PER SHARE 12-Aug-2021","meta":{"isSLBSec":true}},{"symbol":"CHOLAFIN","buyOrderPrice1":0,"buyOrderQty1":0,"sellOrderPrice1":0,"sellQty1":0,"lastTradedPrice":0,"underLyingLtp":672.75,"futuresLtp":672.55,"spread":0.2,"spreadPer":0.03,"openPositions":0,"annualisedYieldPer":0,"volume":0,"turnOver":0,"transactionValue":0,"caExpDate":"21-Jul-2022","ca":"DIVIDEND - RS 0.70 PER SHARE 21-Jul-2022","meta":{"isSLBSec":true}},{"symbol":"DABUR","buyOrderPrice1":0,"buyOrderQty1":0,"sellOrderPrice1":0,"sellQty1":0,"lastTradedPrice":0,"underLyingLtp":564,"futuresLtp":563.9,"spread":0.1,"spreadPer":0.02,"openPositions":0,"annualisedYieldPer":0,"volume":0,"turnOver":0,"transactionValue":0,"caExpDate":"21-Jul-2022","ca":"ANNUAL GENERAL MEETING/DIVIDEND - RS  2.70 PER SHARE 21-Jul-2022","meta":{"isSLBSec":true}},{"symbol":"HCLTECH","buyOrderPrice1":0,"buyOrderQty1":0,"sellOrderPrice1":1.99,"sellQty1":700,"lastTradedPrice":0,"underLyingLtp":924.8,"futuresLtp":924.75,"spread":0.05,"spreadPer":0.01,"openPositions":0,"annualisedYieldPer":1.2333747837370244,"volume":0,"turnOver":0,"transactionValue":0,"caExpDate":"19-Jul-2022","ca":"INTERIM DIVIDEND- RS 10 PER SHARE 19-Jul-2022","meta":{"isSLBSec":true}},{"symbol":"LT","buyOrderPrice1":0,"buyOrderQty1":0,"sellOrderPrice1":0.45,"sellQty1":4290,"lastTradedPrice":0,"underLyingLtp":1799.8,"futuresLtp":1799.55,"spread":0.25,"spreadPer":0.01,"openPositions":0,"annualisedYieldPer":1.2675019446605178,"volume":0,"turnOver":0,"transactionValue":0,"caExpDate":"21-Jul-2022","ca":"DIVIDEND - RS 22 PER SHARE 21-Jul-2022","meta":{"isSLBSec":true}},{"symbol":"AARTIIND","buyOrderPrice1":0,"buyOrderQty1":0,"sellOrderPrice1":1,"sellQty1":49,"lastTradedPrice":0,"underLyingLtp":751,"futuresLtp":750.95,"spread":0.05,"spreadPer":0.01,"openPositions":0,"annualisedYieldPer":6.0752330226364855,"volume":0,"turnOver":0,"transactionValue":0,"caExpDate":"15-Feb-2022","ca":"INTERIM DIVIDEND - RE 1 PER SHARE 15-Feb-2022","meta":{"isSLBSec":true}},{"symbol":"GNFC","buyOrderPrice1":0,"buyOrderQty1":0,"sellOrderPrice1":0,"sellQty1":0,"lastTradedPrice":0,"underLyingLtp":678.25,"futuresLtp":678.2,"spread":0.05,"spreadPer":0.01,"openPositions":0,"annualisedYieldPer":0,"volume":0,"turnOver":0,"transactionValue":0,"caExpDate":"18-Aug-2021","ca":" ANNUAL GENERAL MEETING/DIVIDEND - RS 8 PER SHARE 18-Aug-2021","meta":{"isSLBSec":true}},{"symbol":"IRCTC","buyOrderPrice1":4,"buyOrderQty1":4029,"sellOrderPrice1":5,"sellQty1":125,"lastTradedPrice":4,"underLyingLtp":594.5,"futuresLtp":594.5,"spread":0,"spreadPer":0,"openPositions":0,"annualisedYieldPer":30.698065601345668,"volume":971,"turnOver":3884,"transactionValue":582648.55,"caExpDate":"17-Feb-2022","ca":"INTERIM DIVIDEND - RS 2 PER SHARE 17-Feb-2022","meta":{"isSLBSec":true}},{"symbol":"OIL","buyOrderPrice1":0,"buyOrderQty1":0,"sellOrderPrice1":0.99,"sellQty1":983,"lastTradedPrice":0,"underLyingLtp":0,"futuresLtp":0,"spread":0,"spreadPer":0,"openPositions":0,"annualisedYieldPer":0,"volume":0,"turnOver":0,"transactionValue":0,"caExpDate":"22-Feb-2022","ca":"INTERIM DIVIDEND - RS 5.75 PER SH 22-Feb-2022","meta":{"isSLBSec":true}},{"symbol":"PFC","buyOrderPrice1":0,"buyOrderQty1":0,"sellOrderPrice1":0.5,"sellQty1":89,"lastTradedPrice":0,"underLyingLtp":113.1,"futuresLtp":113.1,"spread":0,"spreadPer":0,"openPositions":0,"annualisedYieldPer":0,"volume":0,"turnOver":0,"transactionValue":0,"caExpDate":"09-Jun-2022","ca":"DIVIDEND - RS 1.25 PER SHARE 09-Jun-2022","meta":{"isSLBSec":true}},{"symbol":"MRPL","buyOrderPrice1":0,"buyOrderQty1":0,"sellOrderPrice1":0.98,"sellQty1":680,"lastTradedPrice":0,"underLyingLtp":0,"futuresLtp":0,"spread":0,"spreadPer":0,"openPositions":0,"annualisedYieldPer":0,"volume":0,"turnOver":0,"transactionValue":0,"caExpDate":"25-Aug-2021","ca":" ANNUAL GENERAL MEETING 25-Aug-2021","meta":{"isSLBSec":true}},{"symbol":"NHPC","buyOrderPrice1":0,"buyOrderQty1":0,"sellOrderPrice1":0.25,"sellQty1":95000,"lastTradedPrice":0,"underLyingLtp":0,"futuresLtp":0,"spread":0,"spreadPer":0,"openPositions":0,"annualisedYieldPer":0,"volume":0,"turnOver":0,"transactionValue":0,"caExpDate":"22-Feb-2022","ca":"INTERIM DIVIDEND - RS 1.31 PER SHARE 22-Feb-2022","meta":{"isSLBSec":true}},{"symbol":"YESBANK","buyOrderPrice1":0,"buyOrderQty1":0,"sellOrderPrice1":0.1,"sellQty1":75000,"lastTradedPrice":0,"underLyingLtp":0,"futuresLtp":0,"spread":0,"spreadPer":0,"openPositions":0,"annualisedYieldPer":0,"volume":0,"turnOver":0,"transactionValue":0,"caExpDate":"03-Jun-2019","ca":" ANNUAL GENERAL MEETING/ DIVIDEND - RS 2 PER SHARE 03-Jun-2019","meta":{"isSLBSec":true}},{"symbol":"ULTRACEMCO","buyOrderPrice1":2,"buyOrderQty1":300,"sellOrderPrice1":9.99,"sellQty1":100,"lastTradedPrice":0,"underLyingLtp":6536,"futuresLtp":6536.7,"spread":-0.7,"spreadPer":-0.01,"openPositions":0,"annualisedYieldPer":2.7922276621787026,"volume":0,"turnOver":0,"transactionValue":0,"caExpDate":"02-Aug-2021","ca":" ANNUAL GENERAL MEETING/DIVIDEND - RS 37 PER SHARE 02-Aug-2021","meta":{"isSLBSec":true}},{"symbol":"ACC","buyOrderPrice1":0,"buyOrderQty1":0,"sellOrderPrice1":3.95,"sellQty1":100,"lastTradedPrice":0,"underLyingLtp":2191.35,"futuresLtp":2191.55,"spread":-0.2,"spreadPer":-0.01,"openPositions":0,"annualisedYieldPer":0,"volume":0,"turnOver":0,"transactionValue":0,"caExpDate":"04-Apr-2022","ca":"DIVIDEND - RS 58 PER SHARE 04-Apr-2022","meta":{"isSLBSec":true}},{"symbol":"INDUSINDBK","buyOrderPrice1":0,"buyOrderQty1":0,"sellOrderPrice1":0.5,"sellQty1":11680,"lastTradedPrice":0,"underLyingLtp":981.8,"futuresLtp":982,"spread":-0.2,"spreadPer":-0.02,"openPositions":0,"annualisedYieldPer":2.323538398859238,"volume":0,"turnOver":0,"transactionValue":0,"caExpDate":"17-Aug-2021","ca":" DIVIDEND - RS 5 PER SHARE 17-Aug-2021","meta":{"isSLBSec":true}},{"symbol":"ASTRAL","buyOrderPrice1":0,"buyOrderQty1":0,"sellOrderPrice1":4,"sellQty1":3200,"lastTradedPrice":0,"underLyingLtp":1762.4,"futuresLtp":1762.7,"spread":-0.3,"spreadPer":-0.02,"openPositions":0,"annualisedYieldPer":2.58879936450295,"volume":0,"turnOver":0,"transactionValue":0,"caExpDate":"17-Nov-2021","ca":" INTERIM DIVIDEND - RS 1.25 PER SHARE 17-Nov-2021","meta":{"isSLBSec":true}},{"symbol":"LALPATHLAB","buyOrderPrice1":30,"buyOrderQty1":3944,"sellOrderPrice1":44.99,"sellQty1":20,"lastTradedPrice":30,"underLyingLtp":2123.7,"futuresLtp":2124.15,"spread":-0.45,"spreadPer":-0.02,"openPositions":0,"annualisedYieldPer":64.45119367142253,"volume":8,"turnOver":240,"transactionValue":16876,"caExpDate":"22-Jun-2022","ca":"ANNUAL GENERAL MEETING/DIVIDEND - RS 6 PER SHARE 22-Jun-2022","meta":{"isSLBSec":true}},{"symbol":"MGL","buyOrderPrice1":0,"buyOrderQty1":0,"sellOrderPrice1":4.95,"sellQty1":150,"lastTradedPrice":0,"underLyingLtp":746.85,"futuresLtp":747.1,"spread":-0.25,"spreadPer":-0.03,"openPositions":0,"annualisedYieldPer":0,"volume":0,"turnOver":0,"transactionValue":0,"caExpDate":"17-Feb-2022","ca":"INTERIM DIVIDEND - RS 9.50 PER SHARE 17-Feb-2022","meta":{"isSLBSec":true}},{"symbol":"RAMCOCEM","buyOrderPrice1":12.5,"buyOrderQty1":2493,"sellOrderPrice1":19,"sellQty1":5000,"lastTradedPrice":19.01,"underLyingLtp":719.85,"futuresLtp":720.15,"spread":-0.3,"spreadPer":-0.04,"openPositions":0,"annualisedYieldPer":120.48777523095089,"volume":89770,"turnOver":1223565.1,"transactionValue":64307637.2,"caExpDate":"02-Aug-2022","ca":"ANNUAL GENERAL MEETING/DIVIDEND - RS 3 PER SHARE 02-Aug-2022","meta":{"isSLBSec":true}},{"symbol":"SHREECEM","buyOrderPrice1":126,"buyOrderQty1":500,"sellOrderPrice1":225,"sellQty1":50,"lastTradedPrice":0,"underLyingLtp":21013.3,"futuresLtp":21023.25,"spread":-9.95,"spreadPer":-0.05,"openPositions":0,"annualisedYieldPer":48.85298834547644,"volume":0,"turnOver":0,"transactionValue":0,"caExpDate":"13-Jul-2022","ca":"DIVIDEND - RS 45 PER SHARE 13-Jul-2022","meta":{"isSLBSec":true}},{"symbol":"NAM-INDIA","buyOrderPrice1":2,"buyOrderQty1":6953,"sellOrderPrice1":2.5,"sellQty1":177,"lastTradedPrice":2,"underLyingLtp":281.35,"futuresLtp":281.5,"spread":-0.15,"spreadPer":-0.05,"openPositions":0,"annualisedYieldPer":32.432912742136125,"volume":14047,"turnOver":28094,"transactionValue":3928945.9,"caExpDate":"30-Jun-2022","ca":"DIVIDEND - RS 7.50 PER SHARE 30-Jun-2022","meta":{"isSLBSec":true}},{"symbol":"HDFCBANK","buyOrderPrice1":0,"buyOrderQty1":0,"sellOrderPrice1":0.45,"sellQty1":1990,"lastTradedPrice":0,"underLyingLtp":1403.25,"futuresLtp":1403.9,"spread":-0.65,"spreadPer":-0.05,"openPositions":0,"annualisedYieldPer":0.8128451808302156,"volume":0,"turnOver":0,"transactionValue":0,"caExpDate":"12-May-2022","ca":"DIVIDEND - RS 15.50 PER SHARE 12-May-2022","meta":{"isSLBSec":true}},{"symbol":"NAVINFLUOR","buyOrderPrice1":5,"buyOrderQty1":9000,"sellOrderPrice1":14,"sellQty1":6499,"lastTradedPrice":0,"underLyingLtp":4261.5,"futuresLtp":4263.6,"spread":-2.1,"spreadPer":-0.05,"openPositions":0,"annualisedYieldPer":11.669893230083304,"volume":0,"turnOver":0,"transactionValue":0,"caExpDate":"07-Jul-2022","ca":"DIVIDEND - RS 6 PER SHARE 07-Jul-2022","meta":{"isSLBSec":true}},{"symbol":"BHARATFORG","buyOrderPrice1":3,"buyOrderQty1":28506,"sellOrderPrice1":3.85,"sellQty1":1201,"lastTradedPrice":0,"underLyingLtp":712.8,"futuresLtp":713.2,"spread":-0.4,"spreadPer":-0.06,"openPositions":0,"annualisedYieldPer":25.603254769921442,"volume":0,"turnOver":0,"transactionValue":0,"caExpDate":"14-Jul-2022","ca":"DIVIDEND - RS 5.50 PER SHARE 14-Jul-2022","meta":{"isSLBSec":true}},{"symbol":"MARUTI","buyOrderPrice1":0,"buyOrderQty1":0,"sellOrderPrice1":3.9,"sellQty1":332,"lastTradedPrice":0,"underLyingLtp":8535.65,"futuresLtp":8541.1,"spread":-5.45,"spreadPer":-0.06,"openPositions":0,"annualisedYieldPer":0,"volume":0,"turnOver":0,"transactionValue":0,"caExpDate":"03-Aug-2022","ca":"DIVIDEND - RS 60 PER SHARE 03-Aug-2022","meta":{"isSLBSec":true}},{"symbol":"EICHERMOT","buyOrderPrice1":0,"buyOrderQty1":0,"sellOrderPrice1":7.5,"sellQty1":200,"lastTradedPrice":0,"underLyingLtp":3042.3,"futuresLtp":3044.85,"spread":-2.55,"spreadPer":-0.08,"openPositions":0,"annualisedYieldPer":29.993754725043548,"volume":0,"turnOver":0,"transactionValue":0,"caExpDate":"09-Aug-2021","ca":" ANNUAL GENERAL MEETING/DIVIDEND - RS 17 PER SHARE 09-Aug-2021","meta":{"isSLBSec":true}},{"symbol":"BALRAMCHIN","buyOrderPrice1":0,"buyOrderQty1":0,"sellOrderPrice1":3,"sellQty1":4500,"lastTradedPrice":0,"underLyingLtp":374.15,"futuresLtp":374.5,"spread":-0.35,"spreadPer":-0.09,"openPositions":0,"annualisedYieldPer":18.291460644126687,"volume":0,"turnOver":0,"transactionValue":0,"caExpDate":"11-Feb-2022","ca":"INTERIM DIVIDEND - RS 2.50 PER SHARE 11-Feb-2022","meta":{"isSLBSec":true}},{"symbol":"ATUL","buyOrderPrice1":0,"buyOrderQty1":0,"sellOrderPrice1":24.9,"sellQty1":200,"lastTradedPrice":0,"underLyingLtp":8675.1,"futuresLtp":8685.05,"spread":-9.95,"spreadPer":-0.11,"openPositions":0,"annualisedYieldPer":0,"volume":0,"turnOver":0,"transactionValue":0,"caExpDate":"14-Jul-2022","ca":"ANNUAL GENERAL MEETING/DIVIDEND - RS 25 PER SHARE 14-Jul-2022","meta":{"isSLBSec":true}},{"symbol":"ICICIBANK","buyOrderPrice1":0,"buyOrderQty1":0,"sellOrderPrice1":0.45,"sellQty1":457,"lastTradedPrice":0,"underLyingLtp":802.45,"futuresLtp":803.35,"spread":-0.9,"spreadPer":-0.11,"openPositions":0,"annualisedYieldPer":1.4214281263630133,"volume":0,"turnOver":0,"transactionValue":0,"caExpDate":"08-Aug-2022","ca":"DIVIDEND - RS 5 PER SHARE 08-Aug-2022","meta":{"isSLBSec":true}},{"symbol":"HDFCLIFE","buyOrderPrice1":0,"buyOrderQty1":0,"sellOrderPrice1":0.5,"sellQty1":175,"lastTradedPrice":0,"underLyingLtp":523,"futuresLtp":523.6,"spread":-0.6,"spreadPer":-0.11,"openPositions":0,"annualisedYieldPer":0,"volume":0,"turnOver":0,"transactionValue":0,"caExpDate":"31-May-2022","ca":"DIVIDEND - RS 1.70 PER SHARE 31-May-2022","meta":{"isSLBSec":true}},{"symbol":"M&M","buyOrderPrice1":0,"buyOrderQty1":0,"sellOrderPrice1":1,"sellQty1":2300,"lastTradedPrice":0,"underLyingLtp":1131.5,"futuresLtp":1132.85,"spread":-1.35,"spreadPer":-0.12,"openPositions":0,"annualisedYieldPer":2.0161290322580645,"volume":0,"turnOver":0,"transactionValue":0,"caExpDate":"14-Jul-2022","ca":"ANNUAL GENERAL MEETING/DIVIDEND - RS 11.55 PER SHARE 14-Jul-2022","meta":{"isSLBSec":true}},{"symbol":"JSWSTEEL","buyOrderPrice1":0,"buyOrderQty1":0,"sellOrderPrice1":4,"sellQty1":27,"lastTradedPrice":0,"underLyingLtp":602.9,"futuresLtp":603.65,"spread":-0.75,"spreadPer":-0.12,"openPositions":0,"annualisedYieldPer":30.270359927019406,"volume":0,"turnOver":0,"transactionValue":0,"caExpDate":"04-Jul-2022","ca":"ANNUAL GENERAL MEETING/DIVIDEND - RS 17.35 PER SHARE 04-Jul-2022","meta":{"isSLBSec":true}},{"symbol":"PAGEIND","buyOrderPrice1":0,"buyOrderQty1":0,"sellOrderPrice1":95,"sellQty1":4,"lastTradedPrice":0,"underLyingLtp":46989.9,"futuresLtp":47050.85,"spread":-60.95,"spreadPer":-0.13,"openPositions":0,"annualisedYieldPer":29.138309509064715,"volume":0,"turnOver":0,"transactionValue":0,"caExpDate":"02-Aug-2022","ca":"ANNUAL GENERAL MEETING 02-Aug-2022","meta":{"isSLBSec":true}},{"symbol":"BANKBARODA","buyOrderPrice1":0,"buyOrderQty1":0,"sellOrderPrice1":0.45,"sellQty1":90000,"lastTradedPrice":0,"underLyingLtp":117.55,"futuresLtp":117.7,"spread":-0.15,"spreadPer":-0.13,"openPositions":0,"annualisedYieldPer":0,"volume":0,"turnOver":0,"transactionValue":0,"caExpDate":"17-Jun-2022","ca":"ANNUAL GENERAL MEETING/DIVIDEND - RS 2.85 PER SHARE 17-Jun-2022","meta":{"isSLBSec":true}},{"symbol":"RELIANCE","buyOrderPrice1":0,"buyOrderQty1":0,"sellOrderPrice1":0.45,"sellQty1":8359,"lastTradedPrice":0,"underLyingLtp":2418.7,"futuresLtp":2421.95,"spread":-3.25,"spreadPer":-0.13,"openPositions":0,"annualisedYieldPer":0.6602203663124819,"volume":0,"turnOver":0,"transactionValue":0,"caExpDate":"11-Jun-2021","ca":" DIVIDEND - RS 7 PER SHARE 11-Jun-2021","meta":{"isSLBSec":true}},{"symbol":"ABB","buyOrderPrice1":2,"buyOrderQty1":13508,"sellOrderPrice1":14.9,"sellQty1":300,"lastTradedPrice":0,"underLyingLtp":2720.6,"futuresLtp":2724.45,"spread":-3.85,"spreadPer":-0.14,"openPositions":0,"annualisedYieldPer":16.602495772991254,"volume":0,"turnOver":0,"transactionValue":0,"caExpDate":"27-Apr-2022","ca":"ANNUAL GENERAL MEETING/DIVIDEND - RS 5.20 PER SHARE 27-Apr-2022","meta":{"isSLBSec":true}},{"symbol":"APOLLOHOSP","buyOrderPrice1":0,"buyOrderQty1":0,"sellOrderPrice1":19.9,"sellQty1":125,"lastTradedPrice":0,"underLyingLtp":4129.2,"futuresLtp":4134.8,"spread":-5.6,"spreadPer":-0.14,"openPositions":0,"annualisedYieldPer":0,"volume":0,"turnOver":0,"transactionValue":0,"caExpDate":"18-Aug-2022","ca":"ANNUAL GENERAL MEETING/DIVIDEND - RS 11.75 PER SHARE 18-Aug-2022","meta":{"isSLBSec":true}},{"symbol":"GMRINFRA","buyOrderPrice1":0,"buyOrderQty1":0,"sellOrderPrice1":0.15,"sellQty1":100000,"lastTradedPrice":0,"underLyingLtp":35.35,"futuresLtp":35.4,"spread":-0.05,"spreadPer":-0.14,"openPositions":0,"annualisedYieldPer":0,"volume":0,"turnOver":0,"transactionValue":0,"caExpDate":"11-Jan-2022","ca":"DEMERGER 11-Jan-2022","meta":{"isSLBSec":true}},{"symbol":"ALKEM","buyOrderPrice1":0,"buyOrderQty1":0,"sellOrderPrice1":35,"sellQty1":750,"lastTradedPrice":0,"underLyingLtp":3110,"futuresLtp":3114.55,"spread":-4.55,"spreadPer":-0.15,"openPositions":0,"annualisedYieldPer":0,"volume":0,"turnOver":0,"transactionValue":0,"caExpDate":"08-Aug-2022","ca":"DIVIDEND - RS 4 PER SHARE 08-Aug-2022","meta":{"isSLBSec":true}},{"symbol":"TORNTPOWER","buyOrderPrice1":1,"buyOrderQty1":9000,"sellOrderPrice1":3,"sellQty1":110,"lastTradedPrice":0,"underLyingLtp":507.8,"futuresLtp":508.55,"spread":-0.75,"spreadPer":-0.15,"openPositions":0,"annualisedYieldPer":17.96967309964553,"volume":0,"turnOver":0,"transactionValue":0,"caExpDate":"10-Feb-2022","ca":"INTERIM DIVIDEND - RS 9 PER SHARE 10-Feb-2022","meta":{"isSLBSec":true}},{"symbol":"DIXON","buyOrderPrice1":25,"buyOrderQty1":766,"sellOrderPrice1":38,"sellQty1":250,"lastTradedPrice":25,"underLyingLtp":3730.05,"futuresLtp":3735.55,"spread":-5.5,"spreadPer":-0.15,"openPositions":0,"annualisedYieldPer":30.57934880229487,"volume":7734,"turnOver":192653.94,"transactionValue":28700487.3,"caExpDate":"20-Sep-2021","ca":" ANNUAL GENERAL MEETING/DIVIDEND - RE 1 PER SHARE 20-Sep-2021","meta":{"isSLBSec":true}},{"symbol":"KOTAKBANK","buyOrderPrice1":0,"buyOrderQty1":0,"sellOrderPrice1":0.5,"sellQty1":11000,"lastTradedPrice":0,"underLyingLtp":1747.5,"futuresLtp":1750.5,"spread":-3,"spreadPer":-0.17,"openPositions":0,"annualisedYieldPer":1.2532188841201715,"volume":0,"turnOver":0,"transactionValue":0,"caExpDate":"11-Aug-2021","ca":" DIVIDEND - RS 0.90 PER SHARE 11-Aug-2021","meta":{"isSLBSec":true}},{"symbol":"PERSISTENT","buyOrderPrice1":0,"buyOrderQty1":0,"sellOrderPrice1":9.9,"sellQty1":62,"lastTradedPrice":0,"underLyingLtp":3355.55,"futuresLtp":3361.95,"spread":-6.4,"spreadPer":-0.19,"openPositions":0,"annualisedYieldPer":0,"volume":0,"turnOver":0,"transactionValue":0,"caExpDate":"11-Jul-2022","ca":"ANNUAL GENERAL MEETING/DIVIDEND - RS 11 PER SHARE 11-Jul-2022","meta":{"isSLBSec":true}},{"symbol":"POLYCAB","buyOrderPrice1":10.04,"buyOrderQty1":3622,"sellOrderPrice1":18,"sellQty1":500,"lastTradedPrice":12,"underLyingLtp":2227.65,"futuresLtp":2232.2,"spread":-4.55,"spreadPer":-0.2,"openPositions":0,"annualisedYieldPer":24.577469530671337,"volume":337,"turnOver":3444.14,"transactionValue":747988.35,"caExpDate":"21-Jun-2022","ca":"ANNUAL GENERAL MEETING/DIVIDEND - RS 14 PER SHARE 21-Jun-2022","meta":{"isSLBSec":true}},{"symbol":"COROMANDEL","buyOrderPrice1":0,"buyOrderQty1":0,"sellOrderPrice1":3,"sellQty1":62,"lastTradedPrice":0,"underLyingLtp":1009.8,"futuresLtp":1011.9,"spread":-2.1,"spreadPer":-0.21,"openPositions":0,"annualisedYieldPer":9.036442859972272,"volume":0,"turnOver":0,"transactionValue":0,"caExpDate":"14-Jul-2022","ca":"DIVIDEND - RS 6 PER SHARE 14-Jul-2022","meta":{"isSLBSec":true}},{"symbol":"HAVELLS","buyOrderPrice1":0,"buyOrderQty1":0,"sellOrderPrice1":2,"sellQty1":500,"lastTradedPrice":0,"underLyingLtp":1215.1,"futuresLtp":1217.65,"spread":-2.55,"spreadPer":-0.21,"openPositions":0,"annualisedYieldPer":0,"volume":0,"turnOver":0,"transactionValue":0,"caExpDate":"14-Jun-2022","ca":"ANNUAL GENERAL MEETING/DIVIDEND - RS 4.50 PER SHARE 14-Jun-2022","meta":{"isSLBSec":true}},{"symbol":"MUTHOOTFIN","buyOrderPrice1":0,"buyOrderQty1":0,"sellOrderPrice1":9.9,"sellQty1":167,"lastTradedPrice":0,"underLyingLtp":1021.35,"futuresLtp":1023.55,"spread":-2.2,"spreadPer":-0.22,"openPositions":0,"annualisedYieldPer":0,"volume":0,"turnOver":0,"transactionValue":0,"caExpDate":"25-Apr-2022","ca":"INTERIM DIVIDEND - RS 20 PER SHARE 25-Apr-2022","meta":{"isSLBSec":true}},{"symbol":"HINDPETRO","buyOrderPrice1":0,"buyOrderQty1":0,"sellOrderPrice1":0.5,"sellQty1":1419,"lastTradedPrice":0,"underLyingLtp":231.8,"futuresLtp":232.3,"spread":-0.5,"spreadPer":-0.22,"openPositions":0,"annualisedYieldPer":0,"volume":0,"turnOver":0,"transactionValue":0,"caExpDate":"08-Jul-2021","ca":" DIVIDEND - RS 22.75  PER SHARE 08-Jul-2021","meta":{"isSLBSec":true}},{"symbol":"TECHM","buyOrderPrice1":0,"buyOrderQty1":0,"sellOrderPrice1":1,"sellQty1":125,"lastTradedPrice":0,"underLyingLtp":1006.4,"futuresLtp":1008.7,"spread":-2.3,"spreadPer":-0.23,"openPositions":0,"annualisedYieldPer":0,"volume":0,"turnOver":0,"transactionValue":0,"caExpDate":"21-Jul-2022","ca":"ANNUAL GENERAL MEETING/SPECIAL DIVIDEND - RS 15 PER SHARE/DIVIDEND - RS 15 PER SHARE 21-Jul-2022","meta":{"isSLBSec":true}},{"symbol":"IPCALAB","buyOrderPrice1":1,"buyOrderQty1":4192,"sellOrderPrice1":2.25,"sellQty1":515,"lastTradedPrice":2,"underLyingLtp":985,"futuresLtp":987.5,"spread":-2.5,"spreadPer":-0.25,"openPositions":0,"annualisedYieldPer":9.263959390862944,"volume":6638,"turnOver":13276,"transactionValue":6547723.2,"caExpDate":"03-Aug-2022","ca":"ANNUAL GENERAL MEETING 03-Aug-2022","meta":{"isSLBSec":true}},{"symbol":"JKCEMENT","buyOrderPrice1":0,"buyOrderQty1":0,"sellOrderPrice1":45,"sellQty1":300,"lastTradedPrice":0,"underLyingLtp":2456,"futuresLtp":2462.5,"spread":-6.5,"spreadPer":-0.26,"openPositions":0,"annualisedYieldPer":0,"volume":0,"turnOver":0,"transactionValue":0,"caExpDate":"03-Aug-2021","ca":" ANNUAL GENERAL MEETING/DIVIDEND - RS 15 PER SHARE 03-Aug-2021","meta":{"isSLBSec":true}},{"symbol":"VOLTAS","buyOrderPrice1":0,"buyOrderQty1":0,"sellOrderPrice1":3,"sellQty1":220,"lastTradedPrice":0,"underLyingLtp":960.5,"futuresLtp":963.15,"spread":-2.65,"spreadPer":-0.28,"openPositions":0,"annualisedYieldPer":19.000520562207186,"volume":0,"turnOver":0,"transactionValue":0,"caExpDate":"09-Jun-2022","ca":"ANNUAL GENERAL MEETING/DIVIDEND - RS 5.50 PER SHARE 09-Jun-2022","meta":{"isSLBSec":true}},{"symbol":"HONAUT","buyOrderPrice1":150,"buyOrderQty1":29,"sellOrderPrice1":237.99,"sellQty1":300,"lastTradedPrice":200,"underLyingLtp":39909,"futuresLtp":40021.45,"spread":-112.45,"spreadPer":-0.28,"openPositions":0,"annualisedYieldPer":22.864516775664637,"volume":1,"turnOver":200,"transactionValue":39387.4,"caExpDate":"10-Aug-2021","ca":" DIVIDEND - RS 85 PER SHARE 10-Aug-2021","meta":{"isSLBSec":true}},{"symbol":"SRTRANSFIN","buyOrderPrice1":25,"buyOrderQty1":2000,"sellOrderPrice1":48.75,"sellQty1":150,"lastTradedPrice":0,"underLyingLtp":1458.95,"futuresLtp":1463.7,"spread":-4.75,"spreadPer":-0.33,"openPositions":0,"annualisedYieldPer":125.08996195894309,"volume":0,"turnOver":0,"transactionValue":0,"caExpDate":"15-Jun-2022","ca":"ANNUAL GENERAL MEETING 15-Jun-2022","meta":{"isSLBSec":true}},{"symbol":"DELTACORP","buyOrderPrice1":0,"buyOrderQty1":0,"sellOrderPrice1":1.99,"sellQty1":100,"lastTradedPrice":0,"underLyingLtp":192.65,"futuresLtp":193.3,"spread":-0.65,"spreadPer":-0.34,"openPositions":0,"annualisedYieldPer":0,"volume":0,"turnOver":0,"transactionValue":0,"caExpDate":"11-Aug-2021","ca":" ANNUAL GENERAL MEETING 11-Aug-2021","meta":{"isSLBSec":true}},{"symbol":"CUMMINSIND","buyOrderPrice1":1,"buyOrderQty1":30000,"sellOrderPrice1":4.5,"sellQty1":4350,"lastTradedPrice":0,"underLyingLtp":1187.55,"futuresLtp":1191.55,"spread":-4,"spreadPer":-0.34,"openPositions":0,"annualisedYieldPer":3.8419434971159108,"volume":0,"turnOver":0,"transactionValue":0,"caExpDate":"02-Aug-2022","ca":"ANNUAL GENERAL MEETING/DIVIDEND - RS 10.5 PER SH 02-Aug-2022","meta":{"isSLBSec":true}},{"symbol":"BAJAJ-AUTO","buyOrderPrice1":0,"buyOrderQty1":0,"sellOrderPrice1":9.45,"sellQty1":3500,"lastTradedPrice":0,"underLyingLtp":3856.8,"futuresLtp":3870.15,"spread":-13.35,"spreadPer":-0.35,"openPositions":0,"annualisedYieldPer":9.22720908525202,"volume":0,"turnOver":0,"transactionValue":0,"caExpDate":"30-Jun-2022","ca":"DIVIDEND - RS 140 PER SHARE 30-Jun-2022","meta":{"isSLBSec":true}},{"symbol":"APOLLOTYRE","buyOrderPrice1":0,"buyOrderQty1":0,"sellOrderPrice1":2.9,"sellQty1":1000,"lastTradedPrice":0,"underLyingLtp":211.8,"futuresLtp":212.55,"spread":-0.75,"spreadPer":-0.35,"openPositions":0,"annualisedYieldPer":21.54154863078376,"volume":0,"turnOver":0,"transactionValue":0,"caExpDate":"16-Jun-2022","ca":"ANNUAL GENERAL MEETING/DIVIDEND - RS 3.25 PER SHARE 16-Jun-2022","meta":{"isSLBSec":true}},{"symbol":"ICICIPRULI","buyOrderPrice1":0,"buyOrderQty1":0,"sellOrderPrice1":1,"sellQty1":984,"lastTradedPrice":0,"underLyingLtp":528,"futuresLtp":529.9,"spread":-1.9,"spreadPer":-0.36,"openPositions":0,"annualisedYieldPer":25.923295454545453,"volume":0,"turnOver":0,"transactionValue":0,"caExpDate":"16-Jun-2022","ca":"DIVIDEND - RS 0.55 PER SHARE 16-Jun-2022","meta":{"isSLBSec":true}},{"symbol":"MFSL","buyOrderPrice1":0,"buyOrderQty1":0,"sellOrderPrice1":2,"sellQty1":55,"lastTradedPrice":0,"underLyingLtp":817.05,"futuresLtp":820.6,"spread":-3.55,"spreadPer":-0.43,"openPositions":0,"annualisedYieldPer":5.58411357934031,"volume":0,"turnOver":0,"transactionValue":0,"caExpDate":"15-Sep-2021","ca":" ANNUAL GENERAL MEETING 15-Sep-2021","meta":{"isSLBSec":true}},{"symbol":"DALBHARAT","buyOrderPrice1":0,"buyOrderQty1":0,"sellOrderPrice1":9.9,"sellQty1":107,"lastTradedPrice":0,"underLyingLtp":1565.65,"futuresLtp":1573.95,"spread":-8.3,"spreadPer":-0.53,"openPositions":0,"annualisedYieldPer":0,"volume":0,"turnOver":0,"transactionValue":0,"caExpDate":"23-Jun-2022","ca":"DIVIDEND - RS 5 PER SHARE 23-Jun-2022","meta":{"isSLBSec":true}}],"timestamp":"27-Jul-2022 13:07:50","meta":"Aug-2022(G1)**","marketStatus":{"market":"SLBS","marketOpenOrClose":"Open","marketCurrentTradingDate":"Jul 27,2022","marketOpenTime":"0915","marketCloseTime":"1700","marketPreviousTradingDate":"Jul 26,2022","marketNextTradingDate":"Jul 28,2022","marketStatusMessage":"Market is Open"}}