{"data":[{"symbol":"LALPATHLAB","buyOrderPrice1":90.11,"buyOrderQty1":2000,"sellOrderPrice1":110,"sellQty1":60,"lastTradedPrice":103,"underLyingLtp":2481.85,"futuresLtp":2467.2,"spread":14.65,"spreadPer":0.59,"openPositions":0,"annualisedYieldPer":189.3496786671233,"volume":2756,"turnOver":287974.44,"transactionValue":7166840.2,"caExpDate":"05-Aug-2022","ca":"INTERIM DIVIDEND - RS 6 PER SHARE 05-Aug-2022","meta":{"isSLBSec":true}},{"symbol":"IDEA","buyOrderPrice1":0,"buyOrderQty1":0,"sellOrderPrice1":0,"sellQty1":0,"lastTradedPrice":0,"underLyingLtp":9.25,"futuresLtp":9.2,"spread":0.05,"spreadPer":0.54,"openPositions":0,"annualisedYieldPer":0,"volume":0,"turnOver":0,"transactionValue":0,"caExpDate":"18-Aug-2022","ca":"ANNUAL GENERAL MEETING 18-Aug-2022","meta":{"isSLBSec":true}},{"symbol":"NTPC","buyOrderPrice1":0,"buyOrderQty1":0,"sellOrderPrice1":0.25,"sellQty1":5158,"lastTradedPrice":0,"underLyingLtp":161.9,"futuresLtp":161.1,"spread":0.8,"spreadPer":0.49,"openPositions":0,"annualisedYieldPer":7.045243977764051,"volume":0,"turnOver":0,"transactionValue":0,"caExpDate":"10-Aug-2022","ca":"DIVIDEND - RS 3 PER SHARE 10-Aug-2022","meta":{"isSLBSec":true}},{"symbol":"CUB","buyOrderPrice1":0,"buyOrderQty1":0,"sellOrderPrice1":0,"sellQty1":0,"lastTradedPrice":0,"underLyingLtp":176.95,"futuresLtp":176.1,"spread":0.85,"spreadPer":0.48,"openPositions":0,"annualisedYieldPer":0,"volume":0,"turnOver":0,"transactionValue":0,"caExpDate":"10-Aug-2022","ca":"DIVIDEND - RE 1 PER SHARE 10-Aug-2022","meta":{"isSLBSec":true}},{"symbol":"CROMPTON","buyOrderPrice1":0,"buyOrderQty1":0,"sellOrderPrice1":2,"sellQty1":2500,"lastTradedPrice":0,"underLyingLtp":386.55,"futuresLtp":384.95,"spread":1.6,"spreadPer":0.41,"openPositions":0,"annualisedYieldPer":0,"volume":0,"turnOver":0,"transactionValue":0,"caExpDate":"07-Jul-2022","ca":"DIVIDEND - RS 2.50 PER SHARE 07-Jul-2022","meta":{"isSLBSec":true}},{"symbol":"BHARTIARTL","buyOrderPrice1":0,"buyOrderQty1":0,"sellOrderPrice1":2.5,"sellQty1":3000,"lastTradedPrice":0,"underLyingLtp":732.5,"futuresLtp":730,"spread":2.5,"spreadPer":0.34,"openPositions":0,"annualisedYieldPer":3.1143344709897613,"volume":0,"turnOver":0,"transactionValue":0,"caExpDate":"01-Aug-2022","ca":"DIVIDEND - RS 3 PER SHARE 01-Aug-2022","meta":{"isSLBSec":true}},{"symbol":"SYNGENE","buyOrderPrice1":2,"buyOrderQty1":18108,"sellOrderPrice1":2.75,"sellQty1":1000,"lastTradedPrice":2.5,"underLyingLtp":614.9,"futuresLtp":613,"spread":1.9,"spreadPer":0.31,"openPositions":0,"annualisedYieldPer":18.549764189299072,"volume":24084,"turnOver":59969.16,"transactionValue":14407048.8,"caExpDate":"30-Jun-2022","ca":"DIVIDEND - RS 0.50 PER SHARE/SPECIAL DIVIDEND - RS 0.50 PER SHARE 30-Jun-2022","meta":{"isSLBSec":true}},{"symbol":"BERGEPAINT","buyOrderPrice1":0,"buyOrderQty1":0,"sellOrderPrice1":0,"sellQty1":0,"lastTradedPrice":0,"underLyingLtp":656.6,"futuresLtp":654.6,"spread":2,"spreadPer":0.3,"openPositions":0,"annualisedYieldPer":0,"volume":0,"turnOver":0,"transactionValue":0,"caExpDate":"18-Aug-2022","ca":"ANNUAL GENERAL MEETING/DIVIDEND - RS 3.10 PER SHARE 18-Aug-2022","meta":{"isSLBSec":true}},{"symbol":"ASTRAL","buyOrderPrice1":1,"buyOrderQty1":2612,"sellOrderPrice1":4,"sellQty1":145,"lastTradedPrice":4,"underLyingLtp":2110.1,"futuresLtp":2104.05,"spread":6.05,"spreadPer":0.29,"openPositions":0,"annualisedYieldPer":8.648879200037914,"volume":1100,"turnOver":4400,"transactionValue":2273865,"caExpDate":"19-Aug-2022","ca":"DIVIDEND - RS 1.75 PER SHARE 19-Aug-2022","meta":{"isSLBSec":true}},{"symbol":"POLYCAB","buyOrderPrice1":8.01,"buyOrderQty1":1450,"sellOrderPrice1":10,"sellQty1":27,"lastTradedPrice":8,"underLyingLtp":2406.45,"futuresLtp":2399.65,"spread":6.8,"spreadPer":0.28,"openPositions":0,"annualisedYieldPer":15.167570487647783,"volume":1310,"turnOver":7768.3,"transactionValue":3154087,"caExpDate":"21-Jun-2022","ca":"ANNUAL GENERAL MEETING/DIVIDEND - RS 14 PER SHARE 21-Jun-2022","meta":{"isSLBSec":true}},{"symbol":"ABFRL","buyOrderPrice1":0,"buyOrderQty1":0,"sellOrderPrice1":0,"sellQty1":0,"lastTradedPrice":0,"underLyingLtp":290.75,"futuresLtp":289.95,"spread":0.8,"spreadPer":0.28,"openPositions":0,"annualisedYieldPer":0,"volume":0,"turnOver":0,"transactionValue":0,"caExpDate":"30-Jun-2020","ca":" RIGHTS 9:77 PARTLY PAID @ PREMIUM RS 100/- 30-Jun-2020","meta":{"isSLBSec":true}},{"symbol":"EICHERMOT","buyOrderPrice1":0,"buyOrderQty1":0,"sellOrderPrice1":9.5,"sellQty1":3350,"lastTradedPrice":0,"underLyingLtp":3440,"futuresLtp":3430.85,"spread":9.15,"spreadPer":0.27,"openPositions":0,"annualisedYieldPer":21.22093023255814,"volume":0,"turnOver":0,"transactionValue":0,"caExpDate":"12-Aug-2022","ca":"ANNUAL GENERAL MEETING/DIVIDEND - RS 21 PER SHARE 12-Aug-2022","meta":{"isSLBSec":true}},{"symbol":"M&MFIN","buyOrderPrice1":0,"buyOrderQty1":0,"sellOrderPrice1":0,"sellQty1":0,"lastTradedPrice":0,"underLyingLtp":196,"futuresLtp":195.5,"spread":0.5,"spreadPer":0.26,"openPositions":0,"annualisedYieldPer":0,"volume":0,"turnOver":0,"transactionValue":0,"caExpDate":"20-Jul-2022","ca":"ANNUAL GENERAL MEETING/DIVIDEND - RS 3.60 PER SHARE 20-Jul-2022","meta":{"isSLBSec":true}},{"symbol":"INTELLECT","buyOrderPrice1":0,"buyOrderQty1":0,"sellOrderPrice1":0,"sellQty1":0,"lastTradedPrice":0,"underLyingLtp":590.95,"futuresLtp":589.4,"spread":1.55,"spreadPer":0.26,"openPositions":0,"annualisedYieldPer":0,"volume":0,"turnOver":0,"transactionValue":0,"caExpDate":"21-Jul-2022","ca":"DIVIDEND - RS 2.5 PER SHARE 21-Jul-2022","meta":{"isSLBSec":true}},{"symbol":"FEDERALBNK","buyOrderPrice1":0,"buyOrderQty1":0,"sellOrderPrice1":0,"sellQty1":0,"lastTradedPrice":0,"underLyingLtp":111.75,"futuresLtp":111.5,"spread":0.25,"spreadPer":0.22,"openPositions":0,"annualisedYieldPer":0,"volume":0,"turnOver":0,"transactionValue":0,"caExpDate":"19-Jul-2022","ca":"ANNUAL GENERAL MEETING/DIVIDEND - RS  1.80 PER SHARE 19-Jul-2022","meta":{"isSLBSec":true}},{"symbol":"MRF","buyOrderPrice1":0,"buyOrderQty1":0,"sellOrderPrice1":899.95,"sellQty1":1,"lastTradedPrice":0,"underLyingLtp":85193,"futuresLtp":85015.5,"spread":177.5,"spreadPer":0.21,"openPositions":0,"annualisedYieldPer":42.843895625227425,"volume":0,"turnOver":0,"transactionValue":0,"caExpDate":"27-Jul-2022","ca":"ANNUAL GENERAL MEETING/DIVIDEND - RS  144 PER SHARE 27-Jul-2022","meta":{"isSLBSec":true}},{"symbol":"ITC","buyOrderPrice1":0,"buyOrderQty1":0,"sellOrderPrice1":0.25,"sellQty1":134200,"lastTradedPrice":0,"underLyingLtp":315.2,"futuresLtp":314.55,"spread":0.65,"spreadPer":0.21,"openPositions":0,"annualisedYieldPer":4.342480964467006,"volume":0,"turnOver":0,"transactionValue":0,"caExpDate":"26-May-2022","ca":"DIVIDEND - RS 6.25 PER SHARE 26-May-2022","meta":{"isSLBSec":true}},{"symbol":"MOTHERSON","buyOrderPrice1":0,"buyOrderQty1":0,"sellOrderPrice1":1.99,"sellQty1":490,"lastTradedPrice":0,"underLyingLtp":124.85,"futuresLtp":124.6,"spread":0.25,"spreadPer":0.2,"openPositions":0,"annualisedYieldPer":0,"volume":0,"turnOver":0,"transactionValue":0,"caExpDate":"12-Aug-2022","ca":"ANNUAL GENERAL MEETING/DIVIDEND - RS  0.65 PER SHARE 12-Aug-2022","meta":{"isSLBSec":true}},{"symbol":"ICICIPRULI","buyOrderPrice1":2.01,"buyOrderQty1":4000,"sellOrderPrice1":0,"sellQty1":0,"lastTradedPrice":2.01,"underLyingLtp":582.85,"futuresLtp":581.8,"spread":1.05,"spreadPer":0.18,"openPositions":0,"annualisedYieldPer":15.734108261130647,"volume":1000,"turnOver":2010,"transactionValue":582560,"caExpDate":"16-Jun-2022","ca":"DIVIDEND - RS 0.55 PER SHARE 16-Jun-2022","meta":{"isSLBSec":true}},{"symbol":"TITAN","buyOrderPrice1":0,"buyOrderQty1":0,"sellOrderPrice1":0,"sellQty1":0,"lastTradedPrice":0,"underLyingLtp":2456.95,"futuresLtp":2452.85,"spread":4.1,"spreadPer":0.17,"openPositions":0,"annualisedYieldPer":0,"volume":0,"turnOver":0,"transactionValue":0,"caExpDate":"08-Jul-2022","ca":"ANNUAL GENERAL MEETING/DIVIDEND - RS 7.50 PER SHARE 08-Jul-2022","meta":{"isSLBSec":true}},{"symbol":"COALINDIA","buyOrderPrice1":0,"buyOrderQty1":0,"sellOrderPrice1":0,"sellQty1":0,"lastTradedPrice":0,"underLyingLtp":223.7,"futuresLtp":223.35,"spread":0.35,"spreadPer":0.16,"openPositions":0,"annualisedYieldPer":0,"volume":0,"turnOver":0,"transactionValue":0,"caExpDate":"11-Aug-2022","ca":"DIVIDEND - RS 3 PER SHARE 11-Aug-2022","meta":{"isSLBSec":true}},{"symbol":"IDFC","buyOrderPrice1":0,"buyOrderQty1":0,"sellOrderPrice1":0,"sellQty1":0,"lastTradedPrice":0,"underLyingLtp":62.5,"futuresLtp":62.4,"spread":0.1,"spreadPer":0.16,"openPositions":0,"annualisedYieldPer":0,"volume":0,"turnOver":0,"transactionValue":0,"caExpDate":"19-Apr-2022","ca":"INTERIM DIVIDEND - RE 1 PER SHARE 19-Apr-2022","meta":{"isSLBSec":true}},{"symbol":"TORNTPHARM","buyOrderPrice1":0,"buyOrderQty1":0,"sellOrderPrice1":0,"sellQty1":0,"lastTradedPrice":0,"underLyingLtp":1547.9,"futuresLtp":1545.35,"spread":2.55,"spreadPer":0.16,"openPositions":0,"annualisedYieldPer":0,"volume":0,"turnOver":0,"transactionValue":0,"caExpDate":"08-Jul-2022","ca":"BONUS 1:1 08-Jul-2022","meta":{"isSLBSec":true}},{"symbol":"INDIGO","buyOrderPrice1":0,"buyOrderQty1":0,"sellOrderPrice1":0,"sellQty1":0,"lastTradedPrice":0,"underLyingLtp":1979.1,"futuresLtp":1976.2,"spread":2.9,"spreadPer":0.15,"openPositions":0,"annualisedYieldPer":0,"volume":0,"turnOver":0,"transactionValue":0,"caExpDate":"18-Aug-2022","ca":"ANNUAL GENERAL MEETING 18-Aug-2022","meta":{"isSLBSec":true}},{"symbol":"AMARAJABAT","buyOrderPrice1":0,"buyOrderQty1":0,"sellOrderPrice1":0,"sellQty1":0,"lastTradedPrice":0,"underLyingLtp":509.7,"futuresLtp":508.95,"spread":0.75,"spreadPer":0.15,"openPositions":0,"annualisedYieldPer":0,"volume":0,"turnOver":0,"transactionValue":0,"caExpDate":"28-Jul-2022","ca":"ANNUAL GENERAL MEETING/DIVIDEND - RS 0.50 PER SHARE 28-Jul-2022","meta":{"isSLBSec":true}},{"symbol":"SBILIFE","buyOrderPrice1":0,"buyOrderQty1":0,"sellOrderPrice1":0,"sellQty1":0,"lastTradedPrice":0,"underLyingLtp":1282,"futuresLtp":1280.05,"spread":1.95,"spreadPer":0.15,"openPositions":0,"annualisedYieldPer":0,"volume":0,"turnOver":0,"transactionValue":0,"caExpDate":"29-Mar-2022","ca":"INTERIM DIVIDEND - RS 2 PER SHARE 29-Mar-2022","meta":{"isSLBSec":true}},{"symbol":"ZYDUSLIFE","buyOrderPrice1":0,"buyOrderQty1":0,"sellOrderPrice1":0,"sellQty1":0,"lastTradedPrice":0,"underLyingLtp":387.5,"futuresLtp":386.95,"spread":0.55,"spreadPer":0.14,"openPositions":0,"annualisedYieldPer":0,"volume":0,"turnOver":0,"transactionValue":0,"caExpDate":"28-Jul-2022","ca":"DIVIDEND - RS 2.50 PER SHARE 28-Jul-2022","meta":{"isSLBSec":true}},{"symbol":"CIPLA","buyOrderPrice1":0,"buyOrderQty1":0,"sellOrderPrice1":0,"sellQty1":0,"lastTradedPrice":0,"underLyingLtp":1035.85,"futuresLtp":1034.4,"spread":1.45,"spreadPer":0.14,"openPositions":0,"annualisedYieldPer":0,"volume":0,"turnOver":0,"transactionValue":0,"caExpDate":"08-Aug-2022","ca":"DIVIDEND - RS 5 PER SHARE 08-Aug-2022","meta":{"isSLBSec":true}},{"symbol":"BIOCON","buyOrderPrice1":0,"buyOrderQty1":0,"sellOrderPrice1":0,"sellQty1":0,"lastTradedPrice":0,"underLyingLtp":306.85,"futuresLtp":306.45,"spread":0.4,"spreadPer":0.13,"openPositions":0,"annualisedYieldPer":0,"volume":0,"turnOver":0,"transactionValue":0,"caExpDate":"30-Jun-2022","ca":"DIVIDEND - RS 0.50 PER SHARE 30-Jun-2022","meta":{"isSLBSec":true}},{"symbol":"L&TFH","buyOrderPrice1":0,"buyOrderQty1":0,"sellOrderPrice1":0,"sellQty1":0,"lastTradedPrice":0,"underLyingLtp":74.15,"futuresLtp":74.05,"spread":0.1,"spreadPer":0.13,"openPositions":0,"annualisedYieldPer":0,"volume":0,"turnOver":0,"transactionValue":0,"caExpDate":"01-Jul-2022","ca":"DIVIDEND - RS 0.50 PER SHARE 01-Jul-2022","meta":{"isSLBSec":true}},{"symbol":"RBLBANK","buyOrderPrice1":0,"buyOrderQty1":0,"sellOrderPrice1":0,"sellQty1":0,"lastTradedPrice":0,"underLyingLtp":111.15,"futuresLtp":111,"spread":0.15,"spreadPer":0.13,"openPositions":0,"annualisedYieldPer":0,"volume":0,"turnOver":0,"transactionValue":0,"caExpDate":"13-Sep-2021","ca":" ANNUAL GENERAL MEETING 13-Sep-2021","meta":{"isSLBSec":true}},{"symbol":"CHOLAFIN","buyOrderPrice1":0,"buyOrderQty1":0,"sellOrderPrice1":0,"sellQty1":0,"lastTradedPrice":0,"underLyingLtp":795.5,"futuresLtp":794.55,"spread":0.95,"spreadPer":0.12,"openPositions":0,"annualisedYieldPer":0,"volume":0,"turnOver":0,"transactionValue":0,"caExpDate":"21-Jul-2022","ca":"DIVIDEND - RS 0.70 PER SHARE 21-Jul-2022","meta":{"isSLBSec":true}},{"symbol":"MGL","buyOrderPrice1":0,"buyOrderQty1":0,"sellOrderPrice1":0,"sellQty1":0,"lastTradedPrice":0,"underLyingLtp":857.15,"futuresLtp":856.15,"spread":1,"spreadPer":0.12,"openPositions":0,"annualisedYieldPer":0,"volume":0,"turnOver":0,"transactionValue":0,"caExpDate":"11-Aug-2022","ca":"ANNUAL GENERAL MEETING/DIVIDEND - RS 15.5 PER SHARE 11-Aug-2022","meta":{"isSLBSec":true}},{"symbol":"NAVINFLUOR","buyOrderPrice1":0,"buyOrderQty1":0,"sellOrderPrice1":8,"sellQty1":88,"lastTradedPrice":0,"underLyingLtp":4250.05,"futuresLtp":4245,"spread":5.05,"spreadPer":0.12,"openPositions":0,"annualisedYieldPer":13.418959776943801,"volume":0,"turnOver":0,"transactionValue":0,"caExpDate":"07-Jul-2022","ca":"DIVIDEND - RS 6 PER SHARE 07-Jul-2022","meta":{"isSLBSec":true}},{"symbol":"SRTRANSFIN","buyOrderPrice1":0,"buyOrderQty1":0,"sellOrderPrice1":15,"sellQty1":350,"lastTradedPrice":0,"underLyingLtp":1335.9,"futuresLtp":1334.45,"spread":1.45,"spreadPer":0.11,"openPositions":0,"annualisedYieldPer":0,"volume":0,"turnOver":0,"transactionValue":0,"caExpDate":"15-Jun-2022","ca":"ANNUAL GENERAL MEETING 15-Jun-2022","meta":{"isSLBSec":true}},{"symbol":"KOTAKBANK","buyOrderPrice1":0,"buyOrderQty1":0,"sellOrderPrice1":0.5,"sellQty1":554,"lastTradedPrice":0,"underLyingLtp":1862.3,"futuresLtp":1860.25,"spread":2.05,"spreadPer":0.11,"openPositions":0,"annualisedYieldPer":1.2249637544971272,"volume":0,"turnOver":0,"transactionValue":0,"caExpDate":"11-Aug-2022","ca":"DIVIDEND - RS 1.10 PER SHARE 11-Aug-2022","meta":{"isSLBSec":true}},{"symbol":"MARICO","buyOrderPrice1":0,"buyOrderQty1":0,"sellOrderPrice1":0,"sellQty1":0,"lastTradedPrice":0,"underLyingLtp":519.2,"futuresLtp":518.7,"spread":0.5,"spreadPer":0.1,"openPositions":0,"annualisedYieldPer":0,"volume":0,"turnOver":0,"transactionValue":0,"caExpDate":"04-Feb-2022","ca":"INTERIM DIVIDEND - RS 6.25 PER SHARE 04-Feb-2022","meta":{"isSLBSec":true}},{"symbol":"RELIANCE","buyOrderPrice1":0,"buyOrderQty1":0,"sellOrderPrice1":0.5,"sellQty1":7036,"lastTradedPrice":0,"underLyingLtp":2649.55,"futuresLtp":2646.9,"spread":2.65,"spreadPer":0.1,"openPositions":0,"annualisedYieldPer":0.43049763167330296,"volume":0,"turnOver":0,"transactionValue":0,"caExpDate":"18-Aug-2022","ca":"DIVIDEND - RS 8 PER SHARE 18-Aug-2022","meta":{"isSLBSec":true}},{"symbol":"PERSISTENT","buyOrderPrice1":0,"buyOrderQty1":0,"sellOrderPrice1":0,"sellQty1":0,"lastTradedPrice":0,"underLyingLtp":3614,"futuresLtp":3610.25,"spread":3.75,"spreadPer":0.1,"openPositions":0,"annualisedYieldPer":0,"volume":0,"turnOver":0,"transactionValue":0,"caExpDate":"11-Jul-2022","ca":"ANNUAL GENERAL MEETING/DIVIDEND - RS 11 PER SHARE 11-Jul-2022","meta":{"isSLBSec":true}},{"symbol":"DIXON","buyOrderPrice1":0,"buyOrderQty1":0,"sellOrderPrice1":25,"sellQty1":290,"lastTradedPrice":0,"underLyingLtp":4099.6,"futuresLtp":4095.85,"spread":3.75,"spreadPer":0.09,"openPositions":0,"annualisedYieldPer":22.25826909942433,"volume":0,"turnOver":0,"transactionValue":0,"caExpDate":"11-Aug-2022","ca":"ANNUAL GENERAL MEETING/DIVIDEND - RS 2 PER SHARE 11-Aug-2022","meta":{"isSLBSec":true}},{"symbol":"TATACHEM","buyOrderPrice1":0,"buyOrderQty1":0,"sellOrderPrice1":0,"sellQty1":0,"lastTradedPrice":0,"underLyingLtp":1091.45,"futuresLtp":1090.5,"spread":0.95,"spreadPer":0.09,"openPositions":0,"annualisedYieldPer":0,"volume":0,"turnOver":0,"transactionValue":0,"caExpDate":"15-Jun-2022","ca":"ANNUAL GENERAL MEETING/DIVIDEND - RS 12.5 PER SHARE 15-Jun-2022","meta":{"isSLBSec":true}},{"symbol":"BHEL","buyOrderPrice1":0,"buyOrderQty1":0,"sellOrderPrice1":0,"sellQty1":0,"lastTradedPrice":0,"underLyingLtp":52.9,"futuresLtp":52.85,"spread":0.05,"spreadPer":0.09,"openPositions":0,"annualisedYieldPer":0,"volume":0,"turnOver":0,"transactionValue":0,"caExpDate":"15-Sep-2021","ca":" ANNUAL GENERAL MEETING 15-Sep-2021","meta":{"isSLBSec":true}},{"symbol":"ADANIPORTS","buyOrderPrice1":0,"buyOrderQty1":0,"sellOrderPrice1":0,"sellQty1":0,"lastTradedPrice":0,"underLyingLtp":821.75,"futuresLtp":821,"spread":0.75,"spreadPer":0.09,"openPositions":0,"annualisedYieldPer":0,"volume":0,"turnOver":0,"transactionValue":0,"caExpDate":"14-Jul-2022","ca":"DIVIDEND - RS 5 PER SHARE 14-Jul-2022","meta":{"isSLBSec":true}},{"symbol":"BAJAJ-AUTO","buyOrderPrice1":7.01,"buyOrderQty1":5000,"sellOrderPrice1":9.4,"sellQty1":50,"lastTradedPrice":7.02,"underLyingLtp":4066.45,"futuresLtp":4062.95,"spread":3.5,"spreadPer":0.09,"openPositions":0,"annualisedYieldPer":7.876341772307541,"volume":28108,"turnOver":203501.92,"transactionValue":114440878.76,"caExpDate":"30-Jun-2022","ca":"DIVIDEND - RS 140 PER SHARE 30-Jun-2022","meta":{"isSLBSec":true}},{"symbol":"TATASTEEL","buyOrderPrice1":0,"buyOrderQty1":0,"sellOrderPrice1":0.1,"sellQty1":148010,"lastTradedPrice":0,"underLyingLtp":106.15,"futuresLtp":106.05,"spread":0.1,"spreadPer":0.09,"openPositions":0,"annualisedYieldPer":21.920631182289213,"volume":0,"turnOver":0,"transactionValue":0,"caExpDate":"28-Jul-2022","ca":"FACE VALUE SPLIT (SUB-DIVISION) - FROM RS 10/- PER SHARE TO RE 1/- PER SHARE 28-Jul-2022","meta":{"isSLBSec":true}},{"symbol":"LAURUSLABS","buyOrderPrice1":0,"buyOrderQty1":0,"sellOrderPrice1":0,"sellQty1":0,"lastTradedPrice":0,"underLyingLtp":576.45,"futuresLtp":576,"spread":0.45,"spreadPer":0.08,"openPositions":0,"annualisedYieldPer":0,"volume":0,"turnOver":0,"transactionValue":0,"caExpDate":"22-Jun-2022","ca":"ANNUAL GENERAL MEETING 22-Jun-2022","meta":{"isSLBSec":true}},{"symbol":"GSPL","buyOrderPrice1":0,"buyOrderQty1":0,"sellOrderPrice1":0,"sellQty1":0,"lastTradedPrice":0,"underLyingLtp":244,"futuresLtp":243.8,"spread":0.2,"spreadPer":0.08,"openPositions":0,"annualisedYieldPer":0,"volume":0,"turnOver":0,"transactionValue":0,"caExpDate":"08-Sep-2021","ca":" DIVIDEND - RS 2 PER SH 08-Sep-2021","meta":{"isSLBSec":true}},{"symbol":"OFSS","buyOrderPrice1":0,"buyOrderQty1":0,"sellOrderPrice1":5,"sellQty1":87,"lastTradedPrice":0,"underLyingLtp":3231.45,"futuresLtp":3228.9,"spread":2.55,"spreadPer":0.08,"openPositions":0,"annualisedYieldPer":0,"volume":0,"turnOver":0,"transactionValue":0,"caExpDate":"26-Jul-2022","ca":"ANNUAL GENERAL MEETING 26-Jul-2022","meta":{"isSLBSec":true}},{"symbol":"HINDALCO","buyOrderPrice1":0,"buyOrderQty1":0,"sellOrderPrice1":0,"sellQty1":0,"lastTradedPrice":0,"underLyingLtp":428.65,"futuresLtp":428.3,"spread":0.35,"spreadPer":0.08,"openPositions":0,"annualisedYieldPer":0,"volume":0,"turnOver":0,"transactionValue":0,"caExpDate":"11-Aug-2022","ca":"ANNUAL GENERAL MEETING/DIVIDEND - RS 4 PER SHARE 11-Aug-2022","meta":{"isSLBSec":true}},{"symbol":"HAVELLS","buyOrderPrice1":0,"buyOrderQty1":0,"sellOrderPrice1":0,"sellQty1":0,"lastTradedPrice":0,"underLyingLtp":1296,"futuresLtp":1295,"spread":1,"spreadPer":0.08,"openPositions":0,"annualisedYieldPer":0,"volume":0,"turnOver":0,"transactionValue":0,"caExpDate":"14-Jun-2022","ca":"ANNUAL GENERAL MEETING/DIVIDEND - RS 4.50 PER SHARE 14-Jun-2022","meta":{"isSLBSec":true}},{"symbol":"ADANIENT","buyOrderPrice1":0,"buyOrderQty1":0,"sellOrderPrice1":0,"sellQty1":0,"lastTradedPrice":0,"underLyingLtp":3020.95,"futuresLtp":3018.95,"spread":2,"spreadPer":0.07,"openPositions":0,"annualisedYieldPer":0,"volume":0,"turnOver":0,"transactionValue":0,"caExpDate":"14-Jul-2022","ca":"DIVIDEND - RE 1 PER SHARE 14-Jul-2022","meta":{"isSLBSec":true}},{"symbol":"HEROMOTOCO","buyOrderPrice1":0,"buyOrderQty1":0,"sellOrderPrice1":0,"sellQty1":0,"lastTradedPrice":0,"underLyingLtp":2804.9,"futuresLtp":2802.9,"spread":2,"spreadPer":0.07,"openPositions":0,"annualisedYieldPer":0,"volume":0,"turnOver":0,"transactionValue":0,"caExpDate":"27-Jul-2022","ca":"ANNUAL GENERAL MEETING/DIVIDEND - RS  35 PER SHARE 27-Jul-2022","meta":{"isSLBSec":true}},{"symbol":"BRITANNIA","buyOrderPrice1":0,"buyOrderQty1":0,"sellOrderPrice1":0,"sellQty1":0,"lastTradedPrice":0,"underLyingLtp":3640,"futuresLtp":3637.95,"spread":2.05,"spreadPer":0.06,"openPositions":0,"annualisedYieldPer":0,"volume":0,"turnOver":0,"transactionValue":0,"caExpDate":"20-Jun-2022","ca":"ANNUAL GENERAL MEETING/DIVIDEND - RS 56.50 PER SHARE 20-Jun-2022","meta":{"isSLBSec":true}},{"symbol":"GRASIM","buyOrderPrice1":0,"buyOrderQty1":0,"sellOrderPrice1":0,"sellQty1":0,"lastTradedPrice":0,"underLyingLtp":1610,"futuresLtp":1609,"spread":1,"spreadPer":0.06,"openPositions":0,"annualisedYieldPer":0,"volume":0,"turnOver":0,"transactionValue":0,"caExpDate":"11-Aug-2022","ca":"ANNUAL GENERAL MEETING/DIVIDEND - RS 5 PER SHARE/SPECIAL DIVIDEND - RS 5 PER SHARE 11-Aug-2022","meta":{"isSLBSec":true}},{"symbol":"IEX","buyOrderPrice1":0,"buyOrderQty1":0,"sellOrderPrice1":0,"sellQty1":0,"lastTradedPrice":0,"underLyingLtp":158.8,"futuresLtp":158.7,"spread":0.1,"spreadPer":0.06,"openPositions":0,"annualisedYieldPer":0,"volume":0,"turnOver":0,"transactionValue":0,"caExpDate":"24-Aug-2022","ca":"ANNUAL GENERAL MEETING 24-Aug-2022","meta":{"isSLBSec":true}},{"symbol":"SBICARD","buyOrderPrice1":0,"buyOrderQty1":0,"sellOrderPrice1":0,"sellQty1":0,"lastTradedPrice":0,"underLyingLtp":908.8,"futuresLtp":908.25,"spread":0.55,"spreadPer":0.06,"openPositions":0,"annualisedYieldPer":0,"volume":0,"turnOver":0,"transactionValue":0,"caExpDate":"30-Mar-2022","ca":"INTERIM DIVIDEND - RS 2.50 PER SHARE 30-Mar-2022","meta":{"isSLBSec":true}},{"symbol":"LT","buyOrderPrice1":0,"buyOrderQty1":0,"sellOrderPrice1":1,"sellQty1":752,"lastTradedPrice":0,"underLyingLtp":1879.8,"futuresLtp":1878.6,"spread":1.2,"spreadPer":0.06,"openPositions":0,"annualisedYieldPer":0,"volume":0,"turnOver":0,"transactionValue":0,"caExpDate":"21-Jul-2022","ca":"DIVIDEND - RS 22 PER SHARE 21-Jul-2022","meta":{"isSLBSec":true}},{"symbol":"LICHSGFIN","buyOrderPrice1":0,"buyOrderQty1":0,"sellOrderPrice1":0,"sellQty1":0,"lastTradedPrice":0,"underLyingLtp":393.45,"futuresLtp":393.2,"spread":0.25,"spreadPer":0.06,"openPositions":0,"annualisedYieldPer":0,"volume":0,"turnOver":0,"transactionValue":0,"caExpDate":"16-Sep-2021","ca":" ANNUAL GENERAL MEETING/DIVIDEND - RS 8.50 PER SHARE 16-Sep-2021","meta":{"isSLBSec":true}},{"symbol":"JUBLFOOD","buyOrderPrice1":0,"buyOrderQty1":0,"sellOrderPrice1":0,"sellQty1":0,"lastTradedPrice":0,"underLyingLtp":576.25,"futuresLtp":575.9,"spread":0.35,"spreadPer":0.06,"openPositions":0,"annualisedYieldPer":0,"volume":0,"turnOver":0,"transactionValue":0,"caExpDate":"08-Jul-2022","ca":"DIVIDEND - RS 1.20 PER SHARE 08-Jul-2022","meta":{"isSLBSec":true}},{"symbol":"DABUR","buyOrderPrice1":0,"buyOrderQty1":0,"sellOrderPrice1":0,"sellQty1":0,"lastTradedPrice":0,"underLyingLtp":582.9,"futuresLtp":582.6,"spread":0.3,"spreadPer":0.05,"openPositions":0,"annualisedYieldPer":0,"volume":0,"turnOver":0,"transactionValue":0,"caExpDate":"21-Jul-2022","ca":"ANNUAL GENERAL MEETING/DIVIDEND - RS  2.70 PER SHARE 21-Jul-2022","meta":{"isSLBSec":true}},{"symbol":"GODREJCP","buyOrderPrice1":0,"buyOrderQty1":0,"sellOrderPrice1":0,"sellQty1":0,"lastTradedPrice":0,"underLyingLtp":898.85,"futuresLtp":898.4,"spread":0.45,"spreadPer":0.05,"openPositions":0,"annualisedYieldPer":0,"volume":0,"turnOver":0,"transactionValue":0,"caExpDate":"05-Feb-2020","ca":" INTERIM DIVIDEND - RS 2 PER SHARE 05-Feb-2020","meta":{"isSLBSec":true}},{"symbol":"HDFC","buyOrderPrice1":0.25,"buyOrderQty1":454,"sellOrderPrice1":0.5,"sellQty1":1100,"lastTradedPrice":0.25,"underLyingLtp":2439.1,"futuresLtp":2437.95,"spread":1.15,"spreadPer":0.05,"openPositions":0,"annualisedYieldPer":0.46764175310565376,"volume":646,"turnOver":161.5,"transactionValue":1563966,"caExpDate":"31-May-2022","ca":"DIVIDEND - RS 30 PER SHARE 31-May-2022","meta":{"isSLBSec":true}},{"symbol":"MANAPPURAM","buyOrderPrice1":0,"buyOrderQty1":0,"sellOrderPrice1":1,"sellQty1":3900,"lastTradedPrice":0,"underLyingLtp":102,"futuresLtp":101.95,"spread":0.05,"spreadPer":0.05,"openPositions":0,"annualisedYieldPer":0,"volume":0,"turnOver":0,"transactionValue":0,"caExpDate":"17-Aug-2022","ca":"INTERIM DIVIDEND - RS  0.75 PER SHARE 17-Aug-2022","meta":{"isSLBSec":true}},{"symbol":"LTTS","buyOrderPrice1":0,"buyOrderQty1":0,"sellOrderPrice1":0,"sellQty1":0,"lastTradedPrice":0,"underLyingLtp":3671.8,"futuresLtp":3670,"spread":1.8,"spreadPer":0.05,"openPositions":0,"annualisedYieldPer":0,"volume":0,"turnOver":0,"transactionValue":0,"caExpDate":"07-Jul-2022","ca":"ANNUAL GENERAL MEETING/DIVIDEND - RS 15 PER SHARE 07-Jul-2022","meta":{"isSLBSec":true}},{"symbol":"BSOFT","buyOrderPrice1":0,"buyOrderQty1":0,"sellOrderPrice1":0,"sellQty1":0,"lastTradedPrice":0,"underLyingLtp":321.45,"futuresLtp":321.3,"spread":0.15,"spreadPer":0.05,"openPositions":0,"annualisedYieldPer":0,"volume":0,"turnOver":0,"transactionValue":0,"caExpDate":"14-Jul-2022","ca":"BUYBACK 14-Jul-2022","meta":{"isSLBSec":true}},{"symbol":"PFC","buyOrderPrice1":0,"buyOrderQty1":0,"sellOrderPrice1":0.5,"sellQty1":6200,"lastTradedPrice":0,"underLyingLtp":118.25,"futuresLtp":118.2,"spread":0.05,"spreadPer":0.04,"openPositions":0,"annualisedYieldPer":0,"volume":0,"turnOver":0,"transactionValue":0,"caExpDate":"09-Jun-2022","ca":"DIVIDEND - RS 1.25 PER SHARE 09-Jun-2022","meta":{"isSLBSec":true}},{"symbol":"TATACOMM","buyOrderPrice1":0,"buyOrderQty1":0,"sellOrderPrice1":0,"sellQty1":0,"lastTradedPrice":0,"underLyingLtp":1166.85,"futuresLtp":1166.35,"spread":0.5,"spreadPer":0.04,"openPositions":0,"annualisedYieldPer":0,"volume":0,"turnOver":0,"transactionValue":0,"caExpDate":"10-Jun-2022","ca":"ANNUAL GENERAL MEETING/DIVIDEND - RS 20.70 PER SHARE 10-Jun-2022","meta":{"isSLBSec":true}},{"symbol":"MFSL","buyOrderPrice1":0,"buyOrderQty1":0,"sellOrderPrice1":0,"sellQty1":0,"lastTradedPrice":0,"underLyingLtp":796.7,"futuresLtp":796.4,"spread":0.3,"spreadPer":0.04,"openPositions":0,"annualisedYieldPer":0,"volume":0,"turnOver":0,"transactionValue":0,"caExpDate":"17-Aug-2022","ca":"ANNUAL GENERAL MEETING 17-Aug-2022","meta":{"isSLBSec":true}},{"symbol":"MCX","buyOrderPrice1":0,"buyOrderQty1":0,"sellOrderPrice1":0,"sellQty1":0,"lastTradedPrice":0,"underLyingLtp":1296.9,"futuresLtp":1296.4,"spread":0.5,"spreadPer":0.04,"openPositions":0,"annualisedYieldPer":0,"volume":0,"turnOver":0,"transactionValue":0,"caExpDate":"26-Aug-2021","ca":" DIVIDEND - RS 27.60 PER SHARE 26-Aug-2021","meta":{"isSLBSec":true}},{"symbol":"MARUTI","buyOrderPrice1":0,"buyOrderQty1":0,"sellOrderPrice1":0,"sellQty1":0,"lastTradedPrice":0,"underLyingLtp":8695,"futuresLtp":8691.55,"spread":3.45,"spreadPer":0.04,"openPositions":0,"annualisedYieldPer":0,"volume":0,"turnOver":0,"transactionValue":0,"caExpDate":"03-Aug-2022","ca":"DIVIDEND - RS 60 PER SHARE 03-Aug-2022","meta":{"isSLBSec":true}},{"symbol":"TECHM","buyOrderPrice1":0,"buyOrderQty1":0,"sellOrderPrice1":0,"sellQty1":0,"lastTradedPrice":0,"underLyingLtp":1071.5,"futuresLtp":1071.1,"spread":0.4,"spreadPer":0.04,"openPositions":0,"annualisedYieldPer":0,"volume":0,"turnOver":0,"transactionValue":0,"caExpDate":"21-Jul-2022","ca":"ANNUAL GENERAL MEETING/SPECIAL DIVIDEND - RS 15 PER SHARE/DIVIDEND - RS 15 PER SHARE 21-Jul-2022","meta":{"isSLBSec":true}},{"symbol":"NMDC","buyOrderPrice1":0,"buyOrderQty1":0,"sellOrderPrice1":0,"sellQty1":0,"lastTradedPrice":0,"underLyingLtp":121.5,"futuresLtp":121.45,"spread":0.05,"spreadPer":0.04,"openPositions":0,"annualisedYieldPer":0,"volume":0,"turnOver":0,"transactionValue":0,"caExpDate":"22-Aug-2022","ca":"ANNUAL GENERAL MEETING 22-Aug-2022","meta":{"isSLBSec":true}},{"symbol":"GODREJPROP","buyOrderPrice1":0,"buyOrderQty1":0,"sellOrderPrice1":0,"sellQty1":0,"lastTradedPrice":0,"underLyingLtp":1336.95,"futuresLtp":1336.5,"spread":0.45,"spreadPer":0.03,"openPositions":0,"annualisedYieldPer":0,"volume":0,"turnOver":0,"transactionValue":0,"caExpDate":"27-Jul-2015","ca":"ANNUAL GENERAL MEETING/DIVIDEND -  RS 2/- PER SHARE 27-Jul-2015","meta":{"isSLBSec":true}},{"symbol":"BHARATFORG","buyOrderPrice1":0,"buyOrderQty1":0,"sellOrderPrice1":3,"sellQty1":2000,"lastTradedPrice":0,"underLyingLtp":730.2,"futuresLtp":730,"spread":0.2,"spreadPer":0.03,"openPositions":0,"annualisedYieldPer":6.373253903040263,"volume":0,"turnOver":0,"transactionValue":0,"caExpDate":"14-Jul-2022","ca":"DIVIDEND - RS 5.50 PER SHARE 14-Jul-2022","meta":{"isSLBSec":true}},{"symbol":"EXIDEIND","buyOrderPrice1":0,"buyOrderQty1":0,"sellOrderPrice1":0,"sellQty1":0,"lastTradedPrice":0,"underLyingLtp":156.65,"futuresLtp":156.6,"spread":0.05,"spreadPer":0.03,"openPositions":0,"annualisedYieldPer":0,"volume":0,"turnOver":0,"transactionValue":0,"caExpDate":"07-Feb-2022","ca":"INTERIM DIVIDEND - RS 2 PER SHARE 07-Feb-2022","meta":{"isSLBSec":true}},{"symbol":"VOLTAS","buyOrderPrice1":1,"buyOrderQty1":29950,"sellOrderPrice1":1.75,"sellQty1":300,"lastTradedPrice":0,"underLyingLtp":989.45,"futuresLtp":989.15,"spread":0.3,"spreadPer":0.03,"openPositions":0,"annualisedYieldPer":0.9222295214513114,"volume":0,"turnOver":0,"transactionValue":0,"caExpDate":"09-Jun-2022","ca":"ANNUAL GENERAL MEETING/DIVIDEND - RS 5.50 PER SHARE 09-Jun-2022","meta":{"isSLBSec":true}},{"symbol":"BAJAJFINSV","buyOrderPrice1":0,"buyOrderQty1":0,"sellOrderPrice1":0,"sellQty1":0,"lastTradedPrice":0,"underLyingLtp":16298.95,"futuresLtp":16294,"spread":4.95,"spreadPer":0.03,"openPositions":0,"annualisedYieldPer":0,"volume":0,"turnOver":0,"transactionValue":0,"caExpDate":"30-Jun-2022","ca":"DIVIDEND - RS 4 PER SHARE 30-Jun-2022","meta":{"isSLBSec":true}},{"symbol":"DRREDDY","buyOrderPrice1":0,"buyOrderQty1":0,"sellOrderPrice1":4,"sellQty1":500,"lastTradedPrice":0,"underLyingLtp":4226.4,"futuresLtp":4225,"spread":1.4,"spreadPer":0.03,"openPositions":0,"annualisedYieldPer":0,"volume":0,"turnOver":0,"transactionValue":0,"caExpDate":"11-Jul-2022","ca":"ANNUAL GENERAL MEETING/DIVIDEND - RS 30 PER SHARE 11-Jul-2022","meta":{"isSLBSec":true}},{"symbol":"MINDTREE","buyOrderPrice1":0,"buyOrderQty1":0,"sellOrderPrice1":0,"sellQty1":0,"lastTradedPrice":0,"underLyingLtp":3328,"futuresLtp":3327.25,"spread":0.75,"spreadPer":0.02,"openPositions":0,"annualisedYieldPer":0,"volume":0,"turnOver":0,"transactionValue":0,"caExpDate":"05-Jul-2022","ca":"ANNUAL GENERAL MEETING/DIVIDEND - RS 27 PER SHARE 05-Jul-2022","meta":{"isSLBSec":true}},{"symbol":"ASIANPAINT","buyOrderPrice1":0,"buyOrderQty1":0,"sellOrderPrice1":0.5,"sellQty1":17282,"lastTradedPrice":0,"underLyingLtp":3357.75,"futuresLtp":3357.1,"spread":0.65,"spreadPer":0.02,"openPositions":0,"annualisedYieldPer":0.6793984066711339,"volume":0,"turnOver":0,"transactionValue":0,"caExpDate":"09-Jun-2022","ca":"DIVIDEND - RS 15.50 PER SHARE 09-Jun-2022","meta":{"isSLBSec":true}},{"symbol":"PEL","buyOrderPrice1":0,"buyOrderQty1":0,"sellOrderPrice1":0,"sellQty1":0,"lastTradedPrice":0,"underLyingLtp":1958.95,"futuresLtp":1958.5,"spread":0.45,"spreadPer":0.02,"openPositions":0,"annualisedYieldPer":0,"volume":0,"turnOver":0,"transactionValue":0,"caExpDate":"30-Aug-2022","ca":"DEMERGER 30-Aug-2022","meta":{"isSLBSec":true}},{"symbol":"JSWSTEEL","buyOrderPrice1":0,"buyOrderQty1":0,"sellOrderPrice1":0,"sellQty1":0,"lastTradedPrice":0,"underLyingLtp":649.95,"futuresLtp":649.85,"spread":0.1,"spreadPer":0.02,"openPositions":0,"annualisedYieldPer":0,"volume":0,"turnOver":0,"transactionValue":0,"caExpDate":"04-Jul-2022","ca":"ANNUAL GENERAL MEETING/DIVIDEND - RS 17.35 PER SHARE 04-Jul-2022","meta":{"isSLBSec":true}},{"symbol":"ABBOTINDIA","buyOrderPrice1":0,"buyOrderQty1":0,"sellOrderPrice1":0,"sellQty1":0,"lastTradedPrice":0,"underLyingLtp":18913.9,"futuresLtp":18909.85,"spread":4.05,"spreadPer":0.02,"openPositions":0,"annualisedYieldPer":0,"volume":0,"turnOver":0,"transactionValue":0,"caExpDate":"02-Aug-2022","ca":"ANNUAL GENERAL MEETING/DIVIDEND - RS 145 PER SHARE/SPECIAL DIVIDEND- 130 PER SHARE 02-Aug-2022","meta":{"isSLBSec":true}},{"symbol":"HINDPETRO","buyOrderPrice1":0,"buyOrderQty1":0,"sellOrderPrice1":0.5,"sellQty1":400,"lastTradedPrice":0,"underLyingLtp":236.95,"futuresLtp":236.9,"spread":0.05,"spreadPer":0.02,"openPositions":0,"annualisedYieldPer":0,"volume":0,"turnOver":0,"transactionValue":0,"caExpDate":"22-Aug-2022","ca":"DIVIDEND - RS 14 PER SHARE 22-Aug-2022","meta":{"isSLBSec":true}},{"symbol":"TATAPOWER","buyOrderPrice1":0,"buyOrderQty1":0,"sellOrderPrice1":0,"sellQty1":0,"lastTradedPrice":0,"underLyingLtp":228.5,"futuresLtp":228.45,"spread":0.05,"spreadPer":0.02,"openPositions":0,"annualisedYieldPer":0,"volume":0,"turnOver":0,"transactionValue":0,"caExpDate":"15-Jun-2022","ca":"DIVIDEND - RS 1.75 PER SHARE 15-Jun-2022","meta":{"isSLBSec":true}},{"symbol":"IGL","buyOrderPrice1":0,"buyOrderQty1":0,"sellOrderPrice1":0,"sellQty1":0,"lastTradedPrice":0,"underLyingLtp":419.5,"futuresLtp":419.4,"spread":0.1,"spreadPer":0.02,"openPositions":0,"annualisedYieldPer":0,"volume":0,"turnOver":0,"transactionValue":0,"caExpDate":"16-Sep-2021","ca":" ANNUAL GENERAL MEETING/DIVIDEND - RS 3.60 PER SHARE 16-Sep-2021","meta":{"isSLBSec":true}},{"symbol":"TATAMOTORS","buyOrderPrice1":0.25,"buyOrderQty1":1000,"sellOrderPrice1":1,"sellQty1":17424,"lastTradedPrice":0,"underLyingLtp":462.2,"futuresLtp":462.15,"spread":0.05,"spreadPer":0.01,"openPositions":0,"annualisedYieldPer":2.4678169623539596,"volume":0,"turnOver":0,"transactionValue":0,"caExpDate":"18-Jul-2016","ca":" DIVIDEND - RE 0.20/- PER SHARE 18-Jul-2016","meta":{"isSLBSec":true}},{"symbol":"DLF","buyOrderPrice1":0,"buyOrderQty1":0,"sellOrderPrice1":0,"sellQty1":0,"lastTradedPrice":0,"underLyingLtp":370.7,"futuresLtp":370.65,"spread":0.05,"spreadPer":0.01,"openPositions":0,"annualisedYieldPer":0,"volume":0,"turnOver":0,"transactionValue":0,"caExpDate":"02-Aug-2022","ca":"DIVIDEND - RS 3 PER SHARE 02-Aug-2022","meta":{"isSLBSec":true}},{"symbol":"GMRINFRA","buyOrderPrice1":0,"buyOrderQty1":0,"sellOrderPrice1":0.2,"sellQty1":23090,"lastTradedPrice":0,"underLyingLtp":33.5,"futuresLtp":33.5,"spread":0,"spreadPer":0,"openPositions":0,"annualisedYieldPer":0,"volume":0,"turnOver":0,"transactionValue":0,"caExpDate":"11-Jan-2022","ca":"DEMERGER 11-Jan-2022","meta":{"isSLBSec":true}},{"symbol":"OIL","buyOrderPrice1":0,"buyOrderQty1":0,"sellOrderPrice1":0.99,"sellQty1":1966,"lastTradedPrice":0,"underLyingLtp":0,"futuresLtp":0,"spread":0,"spreadPer":0,"openPositions":0,"annualisedYieldPer":0,"volume":0,"turnOver":0,"transactionValue":0,"caExpDate":"22-Feb-2022","ca":"INTERIM DIVIDEND - RS 5.75 PER SH 22-Feb-2022","meta":{"isSLBSec":true}},{"symbol":"MAFANG","buyOrderPrice1":0,"buyOrderQty1":0,"sellOrderPrice1":0.25,"sellQty1":50000,"lastTradedPrice":0,"underLyingLtp":0,"futuresLtp":0,"spread":0,"spreadPer":0,"openPositions":0,"annualisedYieldPer":0,"volume":0,"turnOver":0,"transactionValue":0,"caExpDate":null,"ca":" ","meta":{"isSLBSec":true}},{"symbol":"ESCORTS","buyOrderPrice1":15.01,"buyOrderQty1":5000,"sellOrderPrice1":19.4,"sellQty1":100,"lastTradedPrice":18,"underLyingLtp":1754,"futuresLtp":1754.4,"spread":-0.4,"spreadPer":-0.02,"openPositions":0,"annualisedYieldPer":46.82155074116306,"volume":7232,"turnOver":122510.08,"transactionValue":12832822.4,"caExpDate":"30-Jun-2022","ca":"ANNUAL GENERAL MEETING/DIVIDEND - RS 7 PER SHARE 30-Jun-2022","meta":{"isSLBSec":true}},{"symbol":"ASHOKLEY","buyOrderPrice1":0,"buyOrderQty1":0,"sellOrderPrice1":0.99,"sellQty1":2000,"lastTradedPrice":0,"underLyingLtp":147.55,"futuresLtp":147.6,"spread":-0.05,"spreadPer":-0.03,"openPositions":0,"annualisedYieldPer":0,"volume":0,"turnOver":0,"transactionValue":0,"caExpDate":"14-Jul-2022","ca":"ANNUAL GENERAL MEETING/DIVIDEND - RS 1 PER SHARE 14-Jul-2022","meta":{"isSLBSec":true}},{"symbol":"ABB","buyOrderPrice1":0,"buyOrderQty1":0,"sellOrderPrice1":1.75,"sellQty1":250,"lastTradedPrice":0,"underLyingLtp":2976,"futuresLtp":2976.8,"spread":-0.8,"spreadPer":-0.03,"openPositions":0,"annualisedYieldPer":0,"volume":0,"turnOver":0,"transactionValue":0,"caExpDate":"27-Apr-2022","ca":"ANNUAL GENERAL MEETING/DIVIDEND - RS 5.20 PER SHARE 27-Apr-2022","meta":{"isSLBSec":true}},{"symbol":"CUMMINSIND","buyOrderPrice1":0,"buyOrderQty1":0,"sellOrderPrice1":3,"sellQty1":14800,"lastTradedPrice":0,"underLyingLtp":1190.7,"futuresLtp":1191,"spread":-0.3,"spreadPer":-0.03,"openPositions":0,"annualisedYieldPer":11.495338876291257,"volume":0,"turnOver":0,"transactionValue":0,"caExpDate":"02-Aug-2022","ca":"ANNUAL GENERAL MEETING/DIVIDEND - RS 10.5 PER SH 02-Aug-2022","meta":{"isSLBSec":true}},{"symbol":"ICICIBANK","buyOrderPrice1":0,"buyOrderQty1":0,"sellOrderPrice1":0.5,"sellQty1":13050,"lastTradedPrice":0,"underLyingLtp":869.35,"futuresLtp":869.7,"spread":-0.35,"spreadPer":-0.04,"openPositions":0,"annualisedYieldPer":0,"volume":0,"turnOver":0,"transactionValue":0,"caExpDate":"08-Aug-2022","ca":"DIVIDEND - RS 5 PER SHARE 08-Aug-2022","meta":{"isSLBSec":true}},{"symbol":"WIPRO","buyOrderPrice1":0,"buyOrderQty1":0,"sellOrderPrice1":1.99,"sellQty1":1017,"lastTradedPrice":0,"underLyingLtp":416.5,"futuresLtp":416.65,"spread":-0.15,"spreadPer":-0.04,"openPositions":0,"annualisedYieldPer":2.1908763505402162,"volume":0,"turnOver":0,"transactionValue":0,"caExpDate":"14-Jul-2022","ca":"ANNUAL GENERAL MEETING 14-Jul-2022","meta":{"isSLBSec":true}},{"symbol":"M&M","buyOrderPrice1":0,"buyOrderQty1":0,"sellOrderPrice1":0.1,"sellQty1":4072,"lastTradedPrice":0,"underLyingLtp":1269.75,"futuresLtp":1270.2,"spread":-0.45,"spreadPer":-0.04,"openPositions":0,"annualisedYieldPer":0,"volume":0,"turnOver":0,"transactionValue":0,"caExpDate":"14-Jul-2022","ca":"ANNUAL GENERAL MEETING/DIVIDEND - RS 11.55 PER SHARE 14-Jul-2022","meta":{"isSLBSec":true}},{"symbol":"AARTIIND","buyOrderPrice1":0,"buyOrderQty1":0,"sellOrderPrice1":2,"sellQty1":280,"lastTradedPrice":0,"underLyingLtp":783.6,"futuresLtp":784,"spread":-0.4,"spreadPer":-0.05,"openPositions":0,"annualisedYieldPer":5.822485962225625,"volume":0,"turnOver":0,"transactionValue":0,"caExpDate":"15-Feb-2022","ca":"INTERIM DIVIDEND - RE 1 PER SHARE 15-Feb-2022","meta":{"isSLBSec":true}},{"symbol":"SUNPHARMA","buyOrderPrice1":0,"buyOrderQty1":0,"sellOrderPrice1":0.99,"sellQty1":8000,"lastTradedPrice":0,"underLyingLtp":881.6,"futuresLtp":882,"spread":-0.4,"spreadPer":-0.05,"openPositions":0,"annualisedYieldPer":0,"volume":0,"turnOver":0,"transactionValue":0,"caExpDate":"19-Aug-2022","ca":"DIVIDEND - RS 3 PER SHARE 19-Aug-2022","meta":{"isSLBSec":true}},{"symbol":"ACC","buyOrderPrice1":0,"buyOrderQty1":0,"sellOrderPrice1":6,"sellQty1":500,"lastTradedPrice":0,"underLyingLtp":2292.7,"futuresLtp":2293.9,"spread":-1.2,"spreadPer":-0.05,"openPositions":0,"annualisedYieldPer":0,"volume":0,"turnOver":0,"transactionValue":0,"caExpDate":"04-Apr-2022","ca":"DIVIDEND - RS 58 PER SHARE 04-Apr-2022","meta":{"isSLBSec":true}},{"symbol":"COFORGE","buyOrderPrice1":75,"buyOrderQty1":1979,"sellOrderPrice1":80,"sellQty1":5,"lastTradedPrice":71,"underLyingLtp":3700,"futuresLtp":3703.4,"spread":-3.4,"spreadPer":-0.09,"openPositions":0,"annualisedYieldPer":87.55067567567568,"volume":5240,"turnOver":327500,"transactionValue":19760302,"caExpDate":"03-Aug-2022","ca":"INTERIM DIVIDEND - RS 13 PER SHARE 03-Aug-2022","meta":{"isSLBSec":true}},{"symbol":"IRCTC","buyOrderPrice1":6.11,"buyOrderQty1":1,"sellOrderPrice1":7,"sellQty1":1720,"lastTradedPrice":7,"underLyingLtp":713.8,"futuresLtp":714.5,"spread":-0.7,"spreadPer":-0.1,"openPositions":0,"annualisedYieldPer":44.742925189128606,"volume":66092,"turnOver":457356.64,"transactionValue":47715119.4,"caExpDate":"18-Aug-2022","ca":"ANNUAL GENERAL MEETING/DIVIDEND - RS  1.50 PER SHARE 18-Aug-2022","meta":{"isSLBSec":true}},{"symbol":"HDFCBANK","buyOrderPrice1":0,"buyOrderQty1":0,"sellOrderPrice1":0.5,"sellQty1":11121,"lastTradedPrice":0,"underLyingLtp":1471,"futuresLtp":1472.4,"spread":-1.4,"spreadPer":-0.1,"openPositions":0,"annualisedYieldPer":1.5508157715839566,"volume":0,"turnOver":0,"transactionValue":0,"caExpDate":"12-May-2022","ca":"DIVIDEND - RS 15.50 PER SHARE 12-May-2022","meta":{"isSLBSec":true}},{"symbol":"ONGC","buyOrderPrice1":0,"buyOrderQty1":0,"sellOrderPrice1":0.25,"sellQty1":13339,"lastTradedPrice":0,"underLyingLtp":135.65,"futuresLtp":135.8,"spread":-0.15,"spreadPer":-0.11,"openPositions":0,"annualisedYieldPer":0,"volume":0,"turnOver":0,"transactionValue":0,"caExpDate":"18-Aug-2022","ca":"DIVIDEND - RS 3.25 PER SHARE 18-Aug-2022","meta":{"isSLBSec":true}},{"symbol":"SHREECEM","buyOrderPrice1":322.2,"buyOrderQty1":989,"sellOrderPrice1":0,"sellQty1":0,"lastTradedPrice":320,"underLyingLtp":21426.4,"futuresLtp":21453.2,"spread":-26.8,"spreadPer":-0.13,"openPositions":0,"annualisedYieldPer":68.14023821080536,"volume":812,"turnOver":250437.04,"transactionValue":17414679.8,"caExpDate":"13-Jul-2022","ca":"DIVIDEND - RS 45 PER SHARE 13-Jul-2022","meta":{"isSLBSec":true}},{"symbol":"MUTHOOTFIN","buyOrderPrice1":0,"buyOrderQty1":0,"sellOrderPrice1":9,"sellQty1":2224,"lastTradedPrice":0,"underLyingLtp":1037.2,"futuresLtp":1038.95,"spread":-1.75,"spreadPer":-0.17,"openPositions":0,"annualisedYieldPer":0,"volume":0,"turnOver":0,"transactionValue":0,"caExpDate":"22-Aug-2022","ca":"ANNUAL GENERAL MEETING 22-Aug-2022","meta":{"isSLBSec":true}},{"symbol":"VEDL","buyOrderPrice1":0,"buyOrderQty1":0,"sellOrderPrice1":0.99,"sellQty1":5425,"lastTradedPrice":0,"underLyingLtp":265.55,"futuresLtp":266,"spread":-0.45,"spreadPer":-0.17,"openPositions":0,"annualisedYieldPer":0,"volume":0,"turnOver":0,"transactionValue":0,"caExpDate":"03-Aug-2022","ca":"ANNUAL GENERAL MEETING 03-Aug-2022","meta":{"isSLBSec":true}},{"symbol":"HONAUT","buyOrderPrice1":0,"buyOrderQty1":0,"sellOrderPrice1":89.95,"sellQty1":9,"lastTradedPrice":0,"underLyingLtp":42949,"futuresLtp":43027.4,"spread":-78.4,"spreadPer":-0.18,"openPositions":0,"annualisedYieldPer":10.623064564949127,"volume":0,"turnOver":0,"transactionValue":0,"caExpDate":"08-Aug-2022","ca":"DIVIDEND - RS 90 PER SHARE 08-Aug-2022","meta":{"isSLBSec":true}},{"symbol":"AXISBANK","buyOrderPrice1":0,"buyOrderQty1":0,"sellOrderPrice1":1,"sellQty1":600,"lastTradedPrice":0,"underLyingLtp":747.4,"futuresLtp":748.75,"spread":-1.35,"spreadPer":-0.18,"openPositions":0,"annualisedYieldPer":1.5261238961734012,"volume":0,"turnOver":0,"transactionValue":0,"caExpDate":"07-Jul-2022","ca":"DIVIDEND - RS 1 PER SHARE 07-Jul-2022","meta":{"isSLBSec":true}},{"symbol":"POWERGRID","buyOrderPrice1":0,"buyOrderQty1":0,"sellOrderPrice1":0.25,"sellQty1":2439,"lastTradedPrice":0,"underLyingLtp":226.95,"futuresLtp":227.35,"spread":-0.4,"spreadPer":-0.18,"openPositions":0,"annualisedYieldPer":5.025886759198061,"volume":0,"turnOver":0,"transactionValue":0,"caExpDate":"19-Aug-2022","ca":"ANNUAL GENERAL MEETING/DIVIDEND - RS 2.25 PER SHARE 19-Aug-2022","meta":{"isSLBSec":true}},{"symbol":"RAMCOCEM","buyOrderPrice1":3,"buyOrderQty1":3333,"sellOrderPrice1":9,"sellQty1":71993,"lastTradedPrice":0,"underLyingLtp":750.45,"futuresLtp":751.85,"spread":-1.4,"spreadPer":-0.19,"openPositions":0,"annualisedYieldPer":42.557798654140846,"volume":0,"turnOver":0,"transactionValue":0,"caExpDate":"02-Aug-2022","ca":"ANNUAL GENERAL MEETING/DIVIDEND - RS 3 PER SHARE 02-Aug-2022","meta":{"isSLBSec":true}},{"symbol":"ZEEL","buyOrderPrice1":0,"buyOrderQty1":0,"sellOrderPrice1":1.75,"sellQty1":1349,"lastTradedPrice":0,"underLyingLtp":261,"futuresLtp":261.55,"spread":-0.55,"spreadPer":-0.21,"openPositions":0,"annualisedYieldPer":0,"volume":0,"turnOver":0,"transactionValue":0,"caExpDate":"02-Sep-2021","ca":" ANNUAL GENERAL MEETING/DIVIDEND - RS 2.50 PER SHARE 02-Sep-2021","meta":{"isSLBSec":true}},{"symbol":"BANDHANBNK","buyOrderPrice1":0,"buyOrderQty1":0,"sellOrderPrice1":0.99,"sellQty1":5000,"lastTradedPrice":0,"underLyingLtp":286.6,"futuresLtp":287.2,"spread":-0.6,"spreadPer":-0.21,"openPositions":0,"annualisedYieldPer":7.9596999302163285,"volume":0,"turnOver":0,"transactionValue":0,"caExpDate":"02-Aug-2022","ca":"ANNUAL GENERAL MEETING 02-Aug-2022","meta":{"isSLBSec":true}},{"symbol":"TVSMOTOR","buyOrderPrice1":0,"buyOrderQty1":0,"sellOrderPrice1":2.75,"sellQty1":323,"lastTradedPrice":1,"underLyingLtp":955.25,"futuresLtp":957.4,"spread":-2.15,"spreadPer":-0.23,"openPositions":0,"annualisedYieldPer":4.776236587280816,"volume":100,"turnOver":100,"transactionValue":95615,"caExpDate":"25-Mar-2022","ca":"INTERIM DIVIDEND - RS 3.75 PER SHARE 25-Mar-2022","meta":{"isSLBSec":true}},{"symbol":"GAIL","buyOrderPrice1":0,"buyOrderQty1":0,"sellOrderPrice1":0.5,"sellQty1":12200,"lastTradedPrice":0,"underLyingLtp":131.3,"futuresLtp":131.6,"spread":-0.3,"spreadPer":-0.23,"openPositions":0,"annualisedYieldPer":0,"volume":0,"turnOver":0,"transactionValue":0,"caExpDate":"01-Aug-2022","ca":"DIVIDEND - RS 1 PER SHARE 01-Aug-2022","meta":{"isSLBSec":true}},{"symbol":"DIVISLAB","buyOrderPrice1":0,"buyOrderQty1":0,"sellOrderPrice1":10,"sellQty1":136,"lastTradedPrice":0,"underLyingLtp":3468.05,"futuresLtp":3476.4,"spread":-8.35,"spreadPer":-0.24,"openPositions":0,"annualisedYieldPer":0,"volume":0,"turnOver":0,"transactionValue":0,"caExpDate":"11-Aug-2022","ca":"DIVIDEND - RS 30 PER SHARE 11-Aug-2022","meta":{"isSLBSec":true}},{"symbol":"NAM-INDIA","buyOrderPrice1":0,"buyOrderQty1":0,"sellOrderPrice1":1.75,"sellQty1":100,"lastTradedPrice":0,"underLyingLtp":313.9,"futuresLtp":314.65,"spread":-0.75,"spreadPer":-0.24,"openPositions":0,"annualisedYieldPer":5.087209302325582,"volume":0,"turnOver":0,"transactionValue":0,"caExpDate":"30-Jun-2022","ca":"DIVIDEND - RS 7.50 PER SHARE 30-Jun-2022","meta":{"isSLBSec":true}},{"symbol":"IPCALAB","buyOrderPrice1":5,"buyOrderQty1":300,"sellOrderPrice1":7.95,"sellQty1":740,"lastTradedPrice":7,"underLyingLtp":919.45,"futuresLtp":922.65,"spread":-3.2,"spreadPer":-0.35,"openPositions":0,"annualisedYieldPer":34.735439665017125,"volume":2000,"turnOver":12000,"transactionValue":1859300,"caExpDate":"03-Aug-2022","ca":"ANNUAL GENERAL MEETING 03-Aug-2022","meta":{"isSLBSec":true}},{"symbol":"GUJGASLTD","buyOrderPrice1":7,"buyOrderQty1":10000,"sellOrderPrice1":7.5,"sellQty1":3285,"lastTradedPrice":6.95,"underLyingLtp":477.7,"futuresLtp":479.95,"spread":-2.25,"spreadPer":-0.47,"openPositions":0,"annualisedYieldPer":66.37926522922336,"volume":34851,"turnOver":224091.93,"transactionValue":17266927.95,"caExpDate":"19-Aug-2022","ca":"DIVIDEND - RS 2 PER SHARE 19-Aug-2022","meta":{"isSLBSec":true}}],"timestamp":"24-Aug-2022 14:04:17","meta":"Sep-2022(S1)**","marketStatus":{"market":"SLBS","marketOpenOrClose":"Open","marketCurrentTradingDate":"Aug 24,2022","marketOpenTime":"0915","marketCloseTime":"1700","marketPreviousTradingDate":"Aug 23,2022","marketNextTradingDate":"Aug 25,2022","marketStatusMessage":"Market is Open"}}