{"data":[{"symbol":"BERGEPAINT","buyOrderPrice1":0,"buyOrderQty1":0,"sellOrderPrice1":0,"sellQty1":0,"lastTradedPrice":0,"underLyingLtp":615.35,"futuresLtp":610.8,"spread":4.55,"spreadPer":0.74,"openPositions":0,"annualisedYieldPer":0,"volume":0,"turnOver":0,"transactionValue":0,"caExpDate":"22-Sep-2023","ca":"BONUS 1:5 22-Sep-2023","meta":{"isSLBSec":true}},{"symbol":"BATAINDIA","buyOrderPrice1":5,"buyOrderQty1":4164,"sellOrderPrice1":6,"sellQty1":456,"lastTradedPrice":5,"underLyingLtp":1640,"futuresLtp":1633.5,"spread":6.5,"spreadPer":0.4,"openPositions":0,"annualisedYieldPer":11.128048780487806,"volume":26852,"turnOver":166213.88,"transactionValue":43999687.2,"caExpDate":"03-Aug-2023","ca":"ANNUAL GENERAL MEETING/DIVIDEND - RS  13.50 PER SHARE 03-Aug-2023","meta":{"isSLBSec":true}},{"symbol":"APOLLOTYRE","buyOrderPrice1":0,"buyOrderQty1":0,"sellOrderPrice1":0,"sellQty1":0,"lastTradedPrice":0,"underLyingLtp":376.95,"futuresLtp":375.8,"spread":1.15,"spreadPer":0.31,"openPositions":0,"annualisedYieldPer":0,"volume":0,"turnOver":0,"transactionValue":0,"caExpDate":"14-Jul-2023","ca":"DIVIDEND - RS 4 PER SHARE/ SPECIAL DIVIDEND - RE 0.50 PER SHARE 14-Jul-2023","meta":{"isSLBSec":true}},{"symbol":"TECHM","buyOrderPrice1":0,"buyOrderQty1":0,"sellOrderPrice1":0,"sellQty1":0,"lastTradedPrice":0,"underLyingLtp":1298.15,"futuresLtp":1294.1,"spread":4.05,"spreadPer":0.31,"openPositions":0,"annualisedYieldPer":0,"volume":0,"turnOver":0,"transactionValue":0,"caExpDate":"21-Jul-2023","ca":"ANNUAL GENERAL MEETING/DIVIDEND - RS  32 PER SHARE 21-Jul-2023","meta":{"isSLBSec":true}},{"symbol":"ATUL","buyOrderPrice1":16.1,"buyOrderQty1":300,"sellOrderPrice1":18,"sellQty1":1500,"lastTradedPrice":18,"underLyingLtp":7020,"futuresLtp":7000.1,"spread":19.9,"spreadPer":0.28,"openPositions":0,"annualisedYieldPer":9.35897435897436,"volume":9580,"turnOver":180008.2,"transactionValue":67784727,"caExpDate":"14-Jul-2023","ca":"ANNUAL GENERAL MEETING/DIVIDEND - RS 25 PER SHARE 14-Jul-2023","meta":{"isSLBSec":true}},{"symbol":"IDFC","buyOrderPrice1":0,"buyOrderQty1":0,"sellOrderPrice1":0.5,"sellQty1":200,"lastTradedPrice":0,"underLyingLtp":126.7,"futuresLtp":126.35,"spread":0.35,"spreadPer":0.28,"openPositions":0,"annualisedYieldPer":0,"volume":0,"turnOver":0,"transactionValue":0,"caExpDate":"13-Feb-2023","ca":"SPECIAL DIVIDEND - RS 11 PER SHARE 13-Feb-2023","meta":{"isSLBSec":true}},{"symbol":"LTTS","buyOrderPrice1":10,"buyOrderQty1":2000,"sellOrderPrice1":20,"sellQty1":1820,"lastTradedPrice":20,"underLyingLtp":4705,"futuresLtp":4691.85,"spread":13.15,"spreadPer":0.28,"openPositions":0,"annualisedYieldPer":15.5154091392136,"volume":4985,"turnOver":98154.65,"transactionValue":23286430.5,"caExpDate":"07-Jul-2023","ca":"DIVIDEND - RS 30 PER SHARE 07-Jul-2023","meta":{"isSLBSec":true}},{"symbol":"HDFCAMC","buyOrderPrice1":45.01,"buyOrderQty1":300,"sellOrderPrice1":46,"sellQty1":12,"lastTradedPrice":45,"underLyingLtp":2663.85,"futuresLtp":2657,"spread":6.85,"spreadPer":0.26,"openPositions":0,"annualisedYieldPer":61.65887718903092,"volume":54259,"turnOver":2493743.64,"transactionValue":146602392.1,"caExpDate":"09-Jun-2023","ca":"DIVIDEND - RS 48 PER SHARE 09-Jun-2023","meta":{"isSLBSec":true}},{"symbol":"RAMCOCEM","buyOrderPrice1":1.51,"buyOrderQty1":20000,"sellOrderPrice1":3,"sellQty1":500,"lastTradedPrice":1.5,"underLyingLtp":899.35,"futuresLtp":897.15,"spread":2.2,"spreadPer":0.24,"openPositions":0,"annualisedYieldPer":6.087730027241896,"volume":1115,"turnOver":1672.5,"transactionValue":959123,"caExpDate":"03-Aug-2023","ca":"ANNUAL GENERAL MEETING/DIVIDEND - RS 2 PER SHARE 03-Aug-2023","meta":{"isSLBSec":true}},{"symbol":"ASIANPAINT","buyOrderPrice1":0,"buyOrderQty1":0,"sellOrderPrice1":0.5,"sellQty1":11824,"lastTradedPrice":0,"underLyingLtp":3320,"futuresLtp":3313.45,"spread":6.55,"spreadPer":0.2,"openPositions":0,"annualisedYieldPer":0.2748493975903615,"volume":0,"turnOver":0,"transactionValue":0,"caExpDate":"09-Jun-2023","ca":"DIVIDEND - RS 21.25 PER SHARE 09-Jun-2023","meta":{"isSLBSec":true}},{"symbol":"ASHOKLEY","buyOrderPrice1":0,"buyOrderQty1":0,"sellOrderPrice1":0.98,"sellQty1":1705,"lastTradedPrice":0,"underLyingLtp":180.15,"futuresLtp":179.8,"spread":0.35,"spreadPer":0.19,"openPositions":0,"annualisedYieldPer":5.065223424923674,"volume":0,"turnOver":0,"transactionValue":0,"caExpDate":"07-Jul-2023","ca":"ANNUAL GENERAL MEETING/DIVIDEND - RS 2.60 PER SHARE 07-Jul-2023","meta":{"isSLBSec":true}},{"symbol":"MARUTI","buyOrderPrice1":0,"buyOrderQty1":0,"sellOrderPrice1":5,"sellQty1":374,"lastTradedPrice":0,"underLyingLtp":10615,"futuresLtp":10595.8,"spread":19.2,"spreadPer":0.18,"openPositions":0,"annualisedYieldPer":1.3754121526142253,"volume":0,"turnOver":0,"transactionValue":0,"caExpDate":"03-Aug-2023","ca":"DIVIDEND - RS 90 PER SHARE 03-Aug-2023","meta":{"isSLBSec":true}},{"symbol":"NATIONALUM","buyOrderPrice1":0,"buyOrderQty1":0,"sellOrderPrice1":0,"sellQty1":0,"lastTradedPrice":0,"underLyingLtp":93.55,"futuresLtp":93.4,"spread":0.15,"spreadPer":0.16,"openPositions":0,"annualisedYieldPer":0,"volume":0,"turnOver":0,"transactionValue":0,"caExpDate":"15-Sep-2023","ca":"ANNUAL GENERAL MEETING/DIVIDEND - RE 1 PER SHARE 15-Sep-2023","meta":{"isSLBSec":true}},{"symbol":"IPCALAB","buyOrderPrice1":4,"buyOrderQty1":5092,"sellOrderPrice1":4.15,"sellQty1":500,"lastTradedPrice":4,"underLyingLtp":893,"futuresLtp":891.6,"spread":1.4,"spreadPer":0.16,"openPositions":0,"annualisedYieldPer":16.349384098544235,"volume":10880,"turnOver":43302.4,"transactionValue":9772960,"caExpDate":"22-Nov-2022","ca":"INTERIM DIVIDEND - RS 4 PER SHARE 22-Nov-2022","meta":{"isSLBSec":true}},{"symbol":"SAIL","buyOrderPrice1":0,"buyOrderQty1":0,"sellOrderPrice1":0,"sellQty1":0,"lastTradedPrice":0,"underLyingLtp":92.85,"futuresLtp":92.7,"spread":0.15,"spreadPer":0.16,"openPositions":0,"annualisedYieldPer":0,"volume":0,"turnOver":0,"transactionValue":0,"caExpDate":"20-Sep-2023","ca":"DIVIDEND - RE 0.50 PER SHARE 20-Sep-2023","meta":{"isSLBSec":true}},{"symbol":"INDUSTOWER","buyOrderPrice1":0,"buyOrderQty1":0,"sellOrderPrice1":5,"sellQty1":67,"lastTradedPrice":0,"underLyingLtp":186.6,"futuresLtp":186.3,"spread":0.3,"spreadPer":0.16,"openPositions":0,"annualisedYieldPer":4.890139335476956,"volume":0,"turnOver":0,"transactionValue":0,"caExpDate":"13-May-2022","ca":"INTERIM DIVIDEND - RS 11 PER SHARE 13-May-2022","meta":{"isSLBSec":true}},{"symbol":"TVSMOTOR","buyOrderPrice1":0,"buyOrderQty1":0,"sellOrderPrice1":4,"sellQty1":1273,"lastTradedPrice":0,"underLyingLtp":1505.05,"futuresLtp":1502.85,"spread":2.2,"spreadPer":0.15,"openPositions":0,"annualisedYieldPer":7.275505797149597,"volume":0,"turnOver":0,"transactionValue":0,"caExpDate":"02-Feb-2023","ca":"INTERIM DIVIDEND - RS 5 PER SHARE 02-Feb-2023","meta":{"isSLBSec":true}},{"symbol":"BANKBARODA","buyOrderPrice1":0,"buyOrderQty1":0,"sellOrderPrice1":0,"sellQty1":0,"lastTradedPrice":0,"underLyingLtp":217,"futuresLtp":216.7,"spread":0.3,"spreadPer":0.14,"openPositions":0,"annualisedYieldPer":0,"volume":0,"turnOver":0,"transactionValue":0,"caExpDate":"30-Jun-2023","ca":"ANNUAL GENERAL MEETING/DIVIDEND - RS 5.50 PER SHARE 30-Jun-2023","meta":{"isSLBSec":true}},{"symbol":"PAGEIND","buyOrderPrice1":0,"buyOrderQty1":0,"sellOrderPrice1":99,"sellQty1":4,"lastTradedPrice":0,"underLyingLtp":39650,"futuresLtp":39602.7,"spread":47.3,"spreadPer":0.12,"openPositions":0,"annualisedYieldPer":36.82219419924338,"volume":0,"turnOver":0,"transactionValue":0,"caExpDate":"18-Aug-2023","ca":"INTERIM DIVIDEND - RS 75 PER SHARE 18-Aug-2023","meta":{"isSLBSec":true}},{"symbol":"GAIL","buyOrderPrice1":0,"buyOrderQty1":0,"sellOrderPrice1":0,"sellQty1":0,"lastTradedPrice":0,"underLyingLtp":122.05,"futuresLtp":121.9,"spread":0.15,"spreadPer":0.12,"openPositions":0,"annualisedYieldPer":0,"volume":0,"turnOver":0,"transactionValue":0,"caExpDate":"21-Mar-2023","ca":"INTERIM DIVIDEND - RS 4 PER SHARE 21-Mar-2023","meta":{"isSLBSec":true}},{"symbol":"CANBK","buyOrderPrice1":0,"buyOrderQty1":0,"sellOrderPrice1":0,"sellQty1":0,"lastTradedPrice":0,"underLyingLtp":374.05,"futuresLtp":373.6,"spread":0.45,"spreadPer":0.12,"openPositions":0,"annualisedYieldPer":0,"volume":0,"turnOver":0,"transactionValue":0,"caExpDate":"14-Jun-2023","ca":"DIVIDEND - RS12 PER SHARE 14-Jun-2023","meta":{"isSLBSec":true}},{"symbol":"COALINDIA","buyOrderPrice1":0,"buyOrderQty1":0,"sellOrderPrice1":0,"sellQty1":0,"lastTradedPrice":0,"underLyingLtp":285.1,"futuresLtp":284.8,"spread":0.3,"spreadPer":0.11,"openPositions":0,"annualisedYieldPer":0,"volume":0,"turnOver":0,"transactionValue":0,"caExpDate":"18-Aug-2023","ca":"DIVIDEND - RS 4 PER SHARE 18-Aug-2023","meta":{"isSLBSec":true}},{"symbol":"INDUSINDBK","buyOrderPrice1":0,"buyOrderQty1":0,"sellOrderPrice1":2,"sellQty1":183,"lastTradedPrice":0,"underLyingLtp":1443.6,"futuresLtp":1442.1,"spread":1.5,"spreadPer":0.1,"openPositions":0,"annualisedYieldPer":5.03151842615683,"volume":0,"turnOver":0,"transactionValue":0,"caExpDate":"02-Jun-2023","ca":"DIVIDEND - RS 14 PER SHARE 02-Jun-2023","meta":{"isSLBSec":true}},{"symbol":"GRASIM","buyOrderPrice1":0,"buyOrderQty1":0,"sellOrderPrice1":0,"sellQty1":0,"lastTradedPrice":0,"underLyingLtp":1925.75,"futuresLtp":1923.75,"spread":2,"spreadPer":0.1,"openPositions":0,"annualisedYieldPer":0,"volume":0,"turnOver":0,"transactionValue":0,"caExpDate":"11-Aug-2023","ca":"ANNUAL GENERAL MEETING/DIVIDEND - RS 10 PER SHARE 11-Aug-2023","meta":{"isSLBSec":true}},{"symbol":"BANDHANBNK","buyOrderPrice1":0,"buyOrderQty1":0,"sellOrderPrice1":0.99,"sellQty1":3000,"lastTradedPrice":0,"underLyingLtp":251,"futuresLtp":250.75,"spread":0.25,"spreadPer":0.1,"openPositions":0,"annualisedYieldPer":58.16733067729084,"volume":0,"turnOver":0,"transactionValue":0,"caExpDate":"11-Aug-2023","ca":"ANNUAL GENERAL MEETING/DIVIDEND - RS 1.50 PER SHARE 11-Aug-2023","meta":{"isSLBSec":true}},{"symbol":"HINDUNILVR","buyOrderPrice1":0,"buyOrderQty1":0,"sellOrderPrice1":0,"sellQty1":0,"lastTradedPrice":0,"underLyingLtp":2480,"futuresLtp":2477.55,"spread":2.45,"spreadPer":0.1,"openPositions":0,"annualisedYieldPer":0,"volume":0,"turnOver":0,"transactionValue":0,"caExpDate":"19-Jun-2023","ca":"ANNUAL GENERAL MEETING/DIVIDEND - RS 22 PER SHARE 19-Jun-2023","meta":{"isSLBSec":true}},{"symbol":"INFY","buyOrderPrice1":0,"buyOrderQty1":0,"sellOrderPrice1":1,"sellQty1":1900,"lastTradedPrice":0,"underLyingLtp":1474.45,"futuresLtp":1473,"spread":1.45,"spreadPer":0.1,"openPositions":0,"annualisedYieldPer":1.2377496693682388,"volume":0,"turnOver":0,"transactionValue":0,"caExpDate":"02-Jun-2023","ca":"ANNUAL GENERAL MEETING/DIVIDEND - RS 17.50 PER SHARE 02-Jun-2023","meta":{"isSLBSec":true}},{"symbol":"BPCL","buyOrderPrice1":0,"buyOrderQty1":0,"sellOrderPrice1":0,"sellQty1":0,"lastTradedPrice":0,"underLyingLtp":350.6,"futuresLtp":350.25,"spread":0.35,"spreadPer":0.1,"openPositions":0,"annualisedYieldPer":0,"volume":0,"turnOver":0,"transactionValue":0,"caExpDate":"11-Aug-2023","ca":"DIVIDEND - RS 4 PER SHARE 11-Aug-2023","meta":{"isSLBSec":true}},{"symbol":"SUNTV","buyOrderPrice1":0,"buyOrderQty1":0,"sellOrderPrice1":0,"sellQty1":0,"lastTradedPrice":0,"underLyingLtp":597.4,"futuresLtp":596.85,"spread":0.55,"spreadPer":0.09,"openPositions":0,"annualisedYieldPer":0,"volume":0,"turnOver":0,"transactionValue":0,"caExpDate":"22-Aug-2023","ca":"INTERIM DIVIDEND - RS 6.25 PER SHARE 22-Aug-2023","meta":{"isSLBSec":true}},{"symbol":"ADANIENT","buyOrderPrice1":0,"buyOrderQty1":0,"sellOrderPrice1":0,"sellQty1":0,"lastTradedPrice":0,"underLyingLtp":2458.2,"futuresLtp":2456.05,"spread":2.15,"spreadPer":0.09,"openPositions":0,"annualisedYieldPer":0,"volume":0,"turnOver":0,"transactionValue":0,"caExpDate":"07-Jul-2023","ca":"DIVIDEND - RS 1.20 PER SHARE 07-Jul-2023","meta":{"isSLBSec":true}},{"symbol":"TATACHEM","buyOrderPrice1":0,"buyOrderQty1":0,"sellOrderPrice1":4.49,"sellQty1":101,"lastTradedPrice":0,"underLyingLtp":1043,"futuresLtp":1042.05,"spread":0.95,"spreadPer":0.09,"openPositions":0,"annualisedYieldPer":17.49760306807287,"volume":0,"turnOver":0,"transactionValue":0,"caExpDate":"14-Jun-2023","ca":"ANNUAL GENERAL MEETING/DIVIDEND - RS 17.50 PER SHARE 14-Jun-2023","meta":{"isSLBSec":true}},{"symbol":"CHAMBLFERT","buyOrderPrice1":0,"buyOrderQty1":0,"sellOrderPrice1":0,"sellQty1":0,"lastTradedPrice":0,"underLyingLtp":281.05,"futuresLtp":280.8,"spread":0.25,"spreadPer":0.09,"openPositions":0,"annualisedYieldPer":0,"volume":0,"turnOver":0,"transactionValue":0,"caExpDate":"21-Aug-2023","ca":"DIVIDEND - RS 3 PER SHARE 21-Aug-2023","meta":{"isSLBSec":true}},{"symbol":"NAVINFLUOR","buyOrderPrice1":0,"buyOrderQty1":0,"sellOrderPrice1":9.89,"sellQty1":104,"lastTradedPrice":0,"underLyingLtp":4499.55,"futuresLtp":4495.35,"spread":4.2,"spreadPer":0.09,"openPositions":0,"annualisedYieldPer":0,"volume":0,"turnOver":0,"transactionValue":0,"caExpDate":"07-Jul-2023","ca":"DIVIDEND - RS 7 PER SHARE 07-Jul-2023","meta":{"isSLBSec":true}},{"symbol":"TITAN","buyOrderPrice1":0,"buyOrderQty1":0,"sellOrderPrice1":5,"sellQty1":3654,"lastTradedPrice":0,"underLyingLtp":3295,"futuresLtp":3292,"spread":3,"spreadPer":0.09,"openPositions":0,"annualisedYieldPer":2.215477996965099,"volume":0,"turnOver":0,"transactionValue":0,"caExpDate":"13-Jul-2023","ca":"ANNUAL GENERAL MEETING/DIVIDEND - RS 10 PER SHARE 13-Jul-2023","meta":{"isSLBSec":true}},{"symbol":"TCS","buyOrderPrice1":0,"buyOrderQty1":0,"sellOrderPrice1":2,"sellQty1":109,"lastTradedPrice":0,"underLyingLtp":3575.95,"futuresLtp":3572.65,"spread":3.3,"spreadPer":0.09,"openPositions":0,"annualisedYieldPer":0.81656622715642,"volume":0,"turnOver":0,"transactionValue":0,"caExpDate":"20-Jul-2023","ca":"INTERIM DIVIDEND - RS 9 PER SHARE 20-Jul-2023","meta":{"isSLBSec":true}},{"symbol":"AXISBANK","buyOrderPrice1":0,"buyOrderQty1":0,"sellOrderPrice1":0,"sellQty1":0,"lastTradedPrice":0,"underLyingLtp":1015.85,"futuresLtp":1014.9,"spread":0.95,"spreadPer":0.09,"openPositions":0,"annualisedYieldPer":0,"volume":0,"turnOver":0,"transactionValue":0,"caExpDate":"07-Jul-2023","ca":"DIVIDEND - RE 1 PER SHARE 07-Jul-2023","meta":{"isSLBSec":true}},{"symbol":"KOTAKBANK","buyOrderPrice1":0,"buyOrderQty1":0,"sellOrderPrice1":1,"sellQty1":3210,"lastTradedPrice":0,"underLyingLtp":1777.55,"futuresLtp":1776.15,"spread":1.4,"spreadPer":0.08,"openPositions":0,"annualisedYieldPer":1.026694045174538,"volume":0,"turnOver":0,"transactionValue":0,"caExpDate":"04-Aug-2023","ca":"DIVIDEND - RS 1.50 PER SH 04-Aug-2023","meta":{"isSLBSec":true}},{"symbol":"ZYDUSLIFE","buyOrderPrice1":0,"buyOrderQty1":0,"sellOrderPrice1":1.99,"sellQty1":607,"lastTradedPrice":0,"underLyingLtp":601.65,"futuresLtp":601.15,"spread":0.5,"spreadPer":0.08,"openPositions":0,"annualisedYieldPer":0,"volume":0,"turnOver":0,"transactionValue":0,"caExpDate":"28-Jul-2023","ca":"DIVIDEND - RS 6 PER SHARE 28-Jul-2023","meta":{"isSLBSec":true}},{"symbol":"ACC","buyOrderPrice1":0,"buyOrderQty1":0,"sellOrderPrice1":4.95,"sellQty1":83,"lastTradedPrice":0,"underLyingLtp":1998.95,"futuresLtp":1997.35,"spread":1.6,"spreadPer":0.08,"openPositions":0,"annualisedYieldPer":0,"volume":0,"turnOver":0,"transactionValue":0,"caExpDate":"07-Jul-2023","ca":"DIVIDEND - RS 9.25 PER SHARE 07-Jul-2023","meta":{"isSLBSec":true}},{"symbol":"FEDERALBNK","buyOrderPrice1":0,"buyOrderQty1":0,"sellOrderPrice1":0,"sellQty1":0,"lastTradedPrice":0,"underLyingLtp":146.7,"futuresLtp":146.6,"spread":0.1,"spreadPer":0.07,"openPositions":0,"annualisedYieldPer":0,"volume":0,"turnOver":0,"transactionValue":0,"caExpDate":"11-Aug-2023","ca":"ANNUAL GENERAL MEETING/DIVIDEND - RE 1 PER SHARE 11-Aug-2023","meta":{"isSLBSec":true}},{"symbol":"SBILIFE","buyOrderPrice1":0,"buyOrderQty1":0,"sellOrderPrice1":0,"sellQty1":0,"lastTradedPrice":0,"underLyingLtp":1290.05,"futuresLtp":1289.2,"spread":0.85,"spreadPer":0.07,"openPositions":0,"annualisedYieldPer":0,"volume":0,"turnOver":0,"transactionValue":0,"caExpDate":"16-Mar-2023","ca":"INTERIM DIVIDEND - RS 2.50 PER SHARE 16-Mar-2023","meta":{"isSLBSec":true}},{"symbol":"M&MFIN","buyOrderPrice1":5.02,"buyOrderQty1":5000,"sellOrderPrice1":5.49,"sellQty1":990,"lastTradedPrice":5.01,"underLyingLtp":299.4,"futuresLtp":299.2,"spread":0.2,"spreadPer":0.07,"openPositions":0,"annualisedYieldPer":61.077154308617246,"volume":44747,"turnOver":211205.84,"transactionValue":13762387.32,"caExpDate":"21-Jul-2023","ca":"ANNUAL GENERAL MEETING/DIVIDEND - RS  6 PER SHARE 21-Jul-2023","meta":{"isSLBSec":true}},{"symbol":"NESTLEIND","buyOrderPrice1":0,"buyOrderQty1":0,"sellOrderPrice1":0,"sellQty1":0,"lastTradedPrice":0,"underLyingLtp":22633.35,"futuresLtp":22618.2,"spread":15.15,"spreadPer":0.07,"openPositions":0,"annualisedYieldPer":0,"volume":0,"turnOver":0,"transactionValue":0,"caExpDate":"21-Apr-2023","ca":"FINAL DIVIDEND - RS 75 PER SHARE 21-Apr-2023","meta":{"isSLBSec":true}},{"symbol":"ICICIBANK","buyOrderPrice1":0,"buyOrderQty1":0,"sellOrderPrice1":0,"sellQty1":0,"lastTradedPrice":0,"underLyingLtp":951.25,"futuresLtp":950.6,"spread":0.65,"spreadPer":0.07,"openPositions":0,"annualisedYieldPer":0,"volume":0,"turnOver":0,"transactionValue":0,"caExpDate":"09-Aug-2023","ca":"DIVIDEND - RS 8 PER SHARE 09-Aug-2023","meta":{"isSLBSec":true}},{"symbol":"JUBLFOOD","buyOrderPrice1":5.01,"buyOrderQty1":10000,"sellOrderPrice1":6,"sellQty1":2000,"lastTradedPrice":6,"underLyingLtp":541.05,"futuresLtp":540.65,"spread":0.4,"spreadPer":0.07,"openPositions":0,"annualisedYieldPer":40.476850568339344,"volume":193808,"turnOver":1079510.56,"transactionValue":104074896,"caExpDate":"12-Jul-2023","ca":"DIVIDEND - RS 1.20 PER SHARE 12-Jul-2023","meta":{"isSLBSec":true}},{"symbol":"JINDALSTEL","buyOrderPrice1":0,"buyOrderQty1":0,"sellOrderPrice1":0.99,"sellQty1":735,"lastTradedPrice":0,"underLyingLtp":692.7,"futuresLtp":692.25,"spread":0.45,"spreadPer":0.06,"openPositions":0,"annualisedYieldPer":0,"volume":0,"turnOver":0,"transactionValue":0,"caExpDate":"18-Aug-2023","ca":"DIVIDEND - RS 2 PER SH 18-Aug-2023","meta":{"isSLBSec":true}},{"symbol":"BAJAJFINSV","buyOrderPrice1":0,"buyOrderQty1":0,"sellOrderPrice1":0,"sellQty1":0,"lastTradedPrice":0,"underLyingLtp":1583.45,"futuresLtp":1582.45,"spread":1,"spreadPer":0.06,"openPositions":0,"annualisedYieldPer":0,"volume":0,"turnOver":0,"transactionValue":0,"caExpDate":"30-Jun-2023","ca":"DIVIDEND - RS 0.80 PER SHARE 30-Jun-2023","meta":{"isSLBSec":true}},{"symbol":"UPL","buyOrderPrice1":0,"buyOrderQty1":0,"sellOrderPrice1":2,"sellQty1":62,"lastTradedPrice":0,"underLyingLtp":619.7,"futuresLtp":619.3,"spread":0.4,"spreadPer":0.06,"openPositions":0,"annualisedYieldPer":0,"volume":0,"turnOver":0,"transactionValue":0,"caExpDate":"03-Aug-2023","ca":"ANNUAL GENERAL MEETING/DIVIDEND - RS 10 PER SHARE 03-Aug-2023","meta":{"isSLBSec":true}},{"symbol":"ABFRL","buyOrderPrice1":0,"buyOrderQty1":0,"sellOrderPrice1":0,"sellQty1":0,"lastTradedPrice":0,"underLyingLtp":216.45,"futuresLtp":216.35,"spread":0.1,"spreadPer":0.05,"openPositions":0,"annualisedYieldPer":0,"volume":0,"turnOver":0,"transactionValue":0,"caExpDate":"30-Jun-2020","ca":" RIGHTS 9:77 PARTLY PAID @ PREMIUM RS 100/- 30-Jun-2020","meta":{"isSLBSec":true}},{"symbol":"METROPOLIS","buyOrderPrice1":0,"buyOrderQty1":0,"sellOrderPrice1":0,"sellQty1":0,"lastTradedPrice":0,"underLyingLtp":1438.2,"futuresLtp":1437.6,"spread":0.6,"spreadPer":0.04,"openPositions":0,"annualisedYieldPer":0,"volume":0,"turnOver":0,"transactionValue":0,"caExpDate":"10-Aug-2023","ca":"ANNUAL GENERAL MEETING 10-Aug-2023","meta":{"isSLBSec":true}},{"symbol":"HINDALCO","buyOrderPrice1":0,"buyOrderQty1":0,"sellOrderPrice1":0.99,"sellQty1":582,"lastTradedPrice":0,"underLyingLtp":468.15,"futuresLtp":467.95,"spread":0.2,"spreadPer":0.04,"openPositions":0,"annualisedYieldPer":0,"volume":0,"turnOver":0,"transactionValue":0,"caExpDate":"14-Aug-2023","ca":"ANNUAL GENERAL MEETING/DIVIDEND - RS  3 PER SHARE 14-Aug-2023","meta":{"isSLBSec":true}},{"symbol":"DABUR","buyOrderPrice1":0,"buyOrderQty1":0,"sellOrderPrice1":0,"sellQty1":0,"lastTradedPrice":0,"underLyingLtp":556.85,"futuresLtp":556.6,"spread":0.25,"spreadPer":0.04,"openPositions":0,"annualisedYieldPer":0,"volume":0,"turnOver":0,"transactionValue":0,"caExpDate":"21-Jul-2023","ca":"ANNUAL GENERAL MEETING/DIVIDEND- RS 2.70 PER SHARE 21-Jul-2023","meta":{"isSLBSec":true}},{"symbol":"TATASTEEL","buyOrderPrice1":0,"buyOrderQty1":0,"sellOrderPrice1":0.39,"sellQty1":5000,"lastTradedPrice":0,"underLyingLtp":126.65,"futuresLtp":126.6,"spread":0.05,"spreadPer":0.04,"openPositions":0,"annualisedYieldPer":14.409790761942359,"volume":0,"turnOver":0,"transactionValue":0,"caExpDate":"22-Jun-2023","ca":"ANNUAL GENERAL MEETING/DIVIDEND - RS 3.60 PER SHARE 22-Jun-2023","meta":{"isSLBSec":true}},{"symbol":"TRENT","buyOrderPrice1":0,"buyOrderQty1":0,"sellOrderPrice1":0,"sellQty1":0,"lastTradedPrice":0,"underLyingLtp":2115.9,"futuresLtp":2115,"spread":0.9,"spreadPer":0.04,"openPositions":0,"annualisedYieldPer":0,"volume":0,"turnOver":0,"transactionValue":0,"caExpDate":"25-May-2023","ca":"DIVIDEND - RS 2.20 PER SHARE 25-May-2023","meta":{"isSLBSec":true}},{"symbol":"MUTHOOTFIN","buyOrderPrice1":17.01,"buyOrderQty1":6050,"sellOrderPrice1":19.9,"sellQty1":40,"lastTradedPrice":17,"underLyingLtp":1260,"futuresLtp":1259.45,"spread":0.55,"spreadPer":0.04,"openPositions":0,"annualisedYieldPer":49.24603174603175,"volume":11600,"turnOver":195460,"transactionValue":14931520,"caExpDate":"21-Sep-2023","ca":"ANNUAL GENERAL MEETING 21-Sep-2023","meta":{"isSLBSec":true}},{"symbol":"APOLLOHOSP","buyOrderPrice1":0,"buyOrderQty1":0,"sellOrderPrice1":0,"sellQty1":0,"lastTradedPrice":0,"underLyingLtp":5090.85,"futuresLtp":5088.6,"spread":2.25,"spreadPer":0.04,"openPositions":0,"annualisedYieldPer":0,"volume":0,"turnOver":0,"transactionValue":0,"caExpDate":"18-Aug-2023","ca":"ANNUAL GENERAL MEETING/DIVIDEND - RS 9 PER SHARE 18-Aug-2023","meta":{"isSLBSec":true}},{"symbol":"JSWSTEEL","buyOrderPrice1":0,"buyOrderQty1":0,"sellOrderPrice1":0,"sellQty1":0,"lastTradedPrice":0,"underLyingLtp":776.3,"futuresLtp":776,"spread":0.3,"spreadPer":0.04,"openPositions":0,"annualisedYieldPer":0,"volume":0,"turnOver":0,"transactionValue":0,"caExpDate":"11-Jul-2023","ca":"ANNUAL GENERAL MEETING/DIVIDEND - RS 3.40 PER SHARE 11-Jul-2023","meta":{"isSLBSec":true}},{"symbol":"DIXON","buyOrderPrice1":0,"buyOrderQty1":0,"sellOrderPrice1":0,"sellQty1":0,"lastTradedPrice":0,"underLyingLtp":4887.25,"futuresLtp":4885.95,"spread":1.3,"spreadPer":0.03,"openPositions":0,"annualisedYieldPer":0,"volume":0,"turnOver":0,"transactionValue":0,"caExpDate":"22-Sep-2023","ca":"ANNUAL GENERAL MEETING/DIVIDEND - RS 3 PER SHARE 22-Sep-2023","meta":{"isSLBSec":true}},{"symbol":"BRITANNIA","buyOrderPrice1":0,"buyOrderQty1":0,"sellOrderPrice1":0,"sellQty1":0,"lastTradedPrice":0,"underLyingLtp":4567.3,"futuresLtp":4565.95,"spread":1.35,"spreadPer":0.03,"openPositions":0,"annualisedYieldPer":0,"volume":0,"turnOver":0,"transactionValue":0,"caExpDate":"21-Aug-2023","ca":"ANNUAL GENERAL MEETING 21-Aug-2023","meta":{"isSLBSec":true}},{"symbol":"TATAMOTORS","buyOrderPrice1":0,"buyOrderQty1":0,"sellOrderPrice1":0,"sellQty1":0,"lastTradedPrice":0,"underLyingLtp":619.05,"futuresLtp":618.85,"spread":0.2,"spreadPer":0.03,"openPositions":0,"annualisedYieldPer":0,"volume":0,"turnOver":0,"transactionValue":0,"caExpDate":"28-Jul-2023","ca":"DIVIDEND - RS 2 PER SHARE 28-Jul-2023","meta":{"isSLBSec":true}},{"symbol":"ABBOTINDIA","buyOrderPrice1":0,"buyOrderQty1":0,"sellOrderPrice1":0,"sellQty1":0,"lastTradedPrice":0,"underLyingLtp":22684.8,"futuresLtp":22680.1,"spread":4.7,"spreadPer":0.02,"openPositions":0,"annualisedYieldPer":0,"volume":0,"turnOver":0,"transactionValue":0,"caExpDate":"21-Jul-2023","ca":"DIVIDEND - RS 180 PER SHARE/ SPECIAL DIVIDEND RS 145 PER SHARE 21-Jul-2023","meta":{"isSLBSec":true}},{"symbol":"COROMANDEL","buyOrderPrice1":0,"buyOrderQty1":0,"sellOrderPrice1":0,"sellQty1":0,"lastTradedPrice":0,"underLyingLtp":1115.6,"futuresLtp":1115.5,"spread":0.1,"spreadPer":0.01,"openPositions":0,"annualisedYieldPer":0,"volume":0,"turnOver":0,"transactionValue":0,"caExpDate":"14-Jul-2023","ca":"ANNUAL GENERAL MEETING 14-Jul-2023","meta":{"isSLBSec":true}},{"symbol":"UNICHEMLAB","buyOrderPrice1":0,"buyOrderQty1":0,"sellOrderPrice1":4,"sellQty1":20,"lastTradedPrice":0,"underLyingLtp":0,"futuresLtp":0,"spread":0,"spreadPer":0,"openPositions":0,"annualisedYieldPer":0,"volume":0,"turnOver":0,"transactionValue":0,"caExpDate":"01-Aug-2022","ca":"ANNUAL GENERAL MEETING/DIVIDEND - RS 4 PER SHARE 01-Aug-2022","meta":{"isSLBSec":true}},{"symbol":"IRCON","buyOrderPrice1":1,"buyOrderQty1":70250,"sellOrderPrice1":1.99,"sellQty1":4700,"lastTradedPrice":1,"underLyingLtp":0,"futuresLtp":0,"spread":0,"spreadPer":0,"openPositions":0,"annualisedYieldPer":0,"volume":750,"turnOver":750,"transactionValue":106837.5,"caExpDate":"05-Sep-2023","ca":"ANNUAL GENERAL MEETING/DIVIDEND - RS 1.20 PER SHARE 05-Sep-2023","meta":{"isSLBSec":true}},{"symbol":"IDFCFIRSTB","buyOrderPrice1":0.82,"buyOrderQty1":282100,"sellOrderPrice1":0.85,"sellQty1":20000,"lastTradedPrice":0.82,"underLyingLtp":93.85,"futuresLtp":93.85,"spread":0,"spreadPer":0,"openPositions":0,"annualisedYieldPer":31.891315929675013,"volume":4038164,"turnOver":3593965.96,"transactionValue":381283444.88,"caExpDate":"23-Jul-2018","ca":" DIVIDEND RE 0.75 PER SHARE 23-Jul-2018","meta":{"isSLBSec":true}},{"symbol":"DHANI","buyOrderPrice1":0,"buyOrderQty1":0,"sellOrderPrice1":0.8,"sellQty1":1000,"lastTradedPrice":0,"underLyingLtp":0,"futuresLtp":0,"spread":0,"spreadPer":0,"openPositions":0,"annualisedYieldPer":0,"volume":0,"turnOver":0,"transactionValue":0,"caExpDate":"20-Sep-2023","ca":"ANNUAL GENERAL MEETING 20-Sep-2023","meta":{"isSLBSec":true}},{"symbol":"IRFC","buyOrderPrice1":0,"buyOrderQty1":0,"sellOrderPrice1":1,"sellQty1":71026,"lastTradedPrice":0,"underLyingLtp":0,"futuresLtp":0,"spread":0,"spreadPer":0,"openPositions":0,"annualisedYieldPer":0,"volume":0,"turnOver":0,"transactionValue":0,"caExpDate":"15-Sep-2023","ca":"DIVIDEND - RE 0.70 PER SHARE 15-Sep-2023","meta":{"isSLBSec":true}},{"symbol":"CSBBANK","buyOrderPrice1":0.4,"buyOrderQty1":200,"sellOrderPrice1":1,"sellQty1":500,"lastTradedPrice":0,"underLyingLtp":0,"futuresLtp":0,"spread":0,"spreadPer":0,"openPositions":0,"annualisedYieldPer":0,"volume":0,"turnOver":0,"transactionValue":0,"caExpDate":"01-Aug-2023","ca":"ANNUAL GENERAL MEETING 01-Aug-2023","meta":{"isSLBSec":true}},{"symbol":"SWSOLAR","buyOrderPrice1":0,"buyOrderQty1":0,"sellOrderPrice1":3,"sellQty1":900,"lastTradedPrice":0,"underLyingLtp":0,"futuresLtp":0,"spread":0,"spreadPer":0,"openPositions":0,"annualisedYieldPer":0,"volume":0,"turnOver":0,"transactionValue":0,"caExpDate":"24-Feb-2020","ca":" INTERIM DIVIDEND - RS 6 PER SHARE 24-Feb-2020","meta":{"isSLBSec":true}},{"symbol":"LT","buyOrderPrice1":0,"buyOrderQty1":0,"sellOrderPrice1":0.75,"sellQty1":594,"lastTradedPrice":0,"underLyingLtp":2882.6,"futuresLtp":2882.55,"spread":0.05,"spreadPer":0,"openPositions":0,"annualisedYieldPer":0.3165544994102547,"volume":0,"turnOver":0,"transactionValue":0,"caExpDate":"12-Sep-2023","ca":"BUY BACK 12-Sep-2023","meta":{"isSLBSec":true}},{"symbol":"COCHINSHIP","buyOrderPrice1":0,"buyOrderQty1":0,"sellOrderPrice1":9.99,"sellQty1":771,"lastTradedPrice":5,"underLyingLtp":0,"futuresLtp":0,"spread":0,"spreadPer":0,"openPositions":0,"annualisedYieldPer":0,"volume":1000,"turnOver":5000,"transactionValue":1007150,"caExpDate":"21-Sep-2023","ca":"ANNUAL GENERAL MEETING/DIVIDEND - RS 3 PER SHARE 21-Sep-2023","meta":{"isSLBSec":true}},{"symbol":"SUZLON","buyOrderPrice1":0,"buyOrderQty1":0,"sellOrderPrice1":0.74,"sellQty1":2870,"lastTradedPrice":0,"underLyingLtp":0,"futuresLtp":0,"spread":0,"spreadPer":0,"openPositions":0,"annualisedYieldPer":0,"volume":0,"turnOver":0,"transactionValue":0,"caExpDate":"20-Sep-2023","ca":"ANNUAL GENERAL MEETING 20-Sep-2023","meta":{"isSLBSec":true}},{"symbol":"IOB","buyOrderPrice1":0.25,"buyOrderQty1":10000,"sellOrderPrice1":1,"sellQty1":2000,"lastTradedPrice":0,"underLyingLtp":0,"futuresLtp":0,"spread":0,"spreadPer":0,"openPositions":0,"annualisedYieldPer":0,"volume":0,"turnOver":0,"transactionValue":0,"caExpDate":"30-Jun-2023","ca":"ANNUAL GENERAL MEETING 30-Jun-2023","meta":{"isSLBSec":true}},{"symbol":"BANKINDIA","buyOrderPrice1":0.25,"buyOrderQty1":65000,"sellOrderPrice1":0,"sellQty1":0,"lastTradedPrice":0,"underLyingLtp":0,"futuresLtp":0,"spread":0,"spreadPer":0,"openPositions":0,"annualisedYieldPer":0,"volume":0,"turnOver":0,"transactionValue":0,"caExpDate":"20-Jun-2023","ca":"DIVIDEND - RS 2 PER SHARE 20-Jun-2023","meta":{"isSLBSec":true}},{"symbol":"SUPREMEIND","buyOrderPrice1":0,"buyOrderQty1":0,"sellOrderPrice1":9.9,"sellQty1":750,"lastTradedPrice":0,"underLyingLtp":0,"futuresLtp":0,"spread":0,"spreadPer":0,"openPositions":0,"annualisedYieldPer":0,"volume":0,"turnOver":0,"transactionValue":0,"caExpDate":"21-Jun-2023","ca":"ANNUAL GENERAL MEETING/DIVIDEND - RS 20 PER SHARE 21-Jun-2023","meta":{"isSLBSec":true}},{"symbol":"J&KBANK","buyOrderPrice1":0.55,"buyOrderQty1":10000,"sellOrderPrice1":0,"sellQty1":0,"lastTradedPrice":0,"underLyingLtp":0,"futuresLtp":0,"spread":0,"spreadPer":0,"openPositions":0,"annualisedYieldPer":0,"volume":0,"turnOver":0,"transactionValue":0,"caExpDate":"17-Aug-2023","ca":"ANNUAL GENERAL MEETING/DIVIDEND - RS  0.50 PER SHARE 17-Aug-2023","meta":{"isSLBSec":true}},{"symbol":"SCHNEIDER","buyOrderPrice1":0,"buyOrderQty1":0,"sellOrderPrice1":0,"sellQty1":0,"lastTradedPrice":4,"underLyingLtp":0,"futuresLtp":0,"spread":0,"spreadPer":0,"openPositions":0,"annualisedYieldPer":0,"volume":1500,"turnOver":6000,"transactionValue":528000,"caExpDate":"07-Sep-2023","ca":"ANNUAL GENERAL MEETING 07-Sep-2023","meta":{"isSLBSec":true}},{"symbol":"PAYTM","buyOrderPrice1":0,"buyOrderQty1":0,"sellOrderPrice1":7.5,"sellQty1":400,"lastTradedPrice":0,"underLyingLtp":0,"futuresLtp":0,"spread":0,"spreadPer":0,"openPositions":0,"annualisedYieldPer":0,"volume":0,"turnOver":0,"transactionValue":0,"caExpDate":null,"ca":" ","meta":{"isSLBSec":true}},{"symbol":"TORNTPHARM","buyOrderPrice1":0,"buyOrderQty1":0,"sellOrderPrice1":0,"sellQty1":0,"lastTradedPrice":0,"underLyingLtp":1848.95,"futuresLtp":1848.9,"spread":0.05,"spreadPer":0,"openPositions":0,"annualisedYieldPer":0,"volume":0,"turnOver":0,"transactionValue":0,"caExpDate":"23-Jun-2023","ca":"DIVIDEND - RS 8 PER SHARE 23-Jun-2023","meta":{"isSLBSec":true}},{"symbol":"GLS","buyOrderPrice1":0,"buyOrderQty1":0,"sellOrderPrice1":8,"sellQty1":3091,"lastTradedPrice":0,"underLyingLtp":0,"futuresLtp":0,"spread":0,"spreadPer":0,"openPositions":0,"annualisedYieldPer":0,"volume":0,"turnOver":0,"transactionValue":0,"caExpDate":"22-Sep-2023","ca":"ANNUAL GENERAL MEETING 22-Sep-2023","meta":{"isSLBSec":true}},{"symbol":"TATAMTRDVR","buyOrderPrice1":0.4,"buyOrderQty1":17060,"sellOrderPrice1":0.6,"sellQty1":3100,"lastTradedPrice":0,"underLyingLtp":0,"futuresLtp":0,"spread":0,"spreadPer":0,"openPositions":0,"annualisedYieldPer":0,"volume":0,"turnOver":0,"transactionValue":0,"caExpDate":"28-Jul-2023","ca":"DIVIDEND - RS 2.10 PER SHARE 28-Jul-2023","meta":{"isSLBSec":true}},{"symbol":"CUMMINSIND","buyOrderPrice1":1,"buyOrderQty1":5000,"sellOrderPrice1":2.99,"sellQty1":1010,"lastTradedPrice":3,"underLyingLtp":1715.8,"futuresLtp":1715.95,"spread":-0.15,"spreadPer":-0.01,"openPositions":0,"annualisedYieldPer":6.38186268795897,"volume":7000,"turnOver":21000,"transactionValue":12098450,"caExpDate":"26-Jul-2023","ca":"ANNUAL GENERAL MEETING/DIVIDEND - RS 13 PER SHARE 26-Jul-2023","meta":{"isSLBSec":true}},{"symbol":"LAURUSLABS","buyOrderPrice1":0,"buyOrderQty1":0,"sellOrderPrice1":2.9,"sellQty1":310,"lastTradedPrice":0,"underLyingLtp":387.6,"futuresLtp":387.65,"spread":-0.05,"spreadPer":-0.01,"openPositions":0,"annualisedYieldPer":0,"volume":0,"turnOver":0,"transactionValue":0,"caExpDate":"07-Jul-2023","ca":"ANNUAL GENERAL MEETING 07-Jul-2023","meta":{"isSLBSec":true}},{"symbol":"INDIGO","buyOrderPrice1":0,"buyOrderQty1":0,"sellOrderPrice1":20,"sellQty1":266,"lastTradedPrice":0,"underLyingLtp":2379.45,"futuresLtp":2380.05,"spread":-0.6,"spreadPer":-0.03,"openPositions":0,"annualisedYieldPer":7.669839668831033,"volume":0,"turnOver":0,"transactionValue":0,"caExpDate":"17-Aug-2023","ca":"ANNUAL GENERAL MEETING 17-Aug-2023","meta":{"isSLBSec":true}},{"symbol":"SBICARD","buyOrderPrice1":0,"buyOrderQty1":0,"sellOrderPrice1":6,"sellQty1":500,"lastTradedPrice":0,"underLyingLtp":787,"futuresLtp":787.25,"spread":-0.25,"spreadPer":-0.03,"openPositions":0,"annualisedYieldPer":0,"volume":0,"turnOver":0,"transactionValue":0,"caExpDate":"29-Mar-2023","ca":"INTERIM DIVIDEND - RS 2.50 PER SHARE 29-Mar-2023","meta":{"isSLBSec":true}},{"symbol":"BEL","buyOrderPrice1":0,"buyOrderQty1":0,"sellOrderPrice1":1.5,"sellQty1":2100,"lastTradedPrice":0,"underLyingLtp":135.95,"futuresLtp":136,"spread":-0.05,"spreadPer":-0.04,"openPositions":0,"annualisedYieldPer":0,"volume":0,"turnOver":0,"transactionValue":0,"caExpDate":"17-Aug-2023","ca":"ANNUAL GENERAL MEETING/DIVIDEND - RE 0.60 PER SHARE 17-Aug-2023","meta":{"isSLBSec":true}},{"symbol":"IGL","buyOrderPrice1":0,"buyOrderQty1":0,"sellOrderPrice1":1.99,"sellQty1":259,"lastTradedPrice":0,"underLyingLtp":456,"futuresLtp":456.25,"spread":-0.25,"spreadPer":-0.05,"openPositions":0,"annualisedYieldPer":12.006578947368421,"volume":0,"turnOver":0,"transactionValue":0,"caExpDate":"31-Mar-2023","ca":"INTERIM DIVIDEND - RS 10 PER SHARE 31-Mar-2023","meta":{"isSLBSec":true}},{"symbol":"PERSISTENT","buyOrderPrice1":5,"buyOrderQty1":1000,"sellOrderPrice1":25,"sellQty1":60,"lastTradedPrice":0,"underLyingLtp":5895.85,"futuresLtp":5898.55,"spread":-2.7,"spreadPer":-0.05,"openPositions":0,"annualisedYieldPer":6.531288957487045,"volume":0,"turnOver":0,"transactionValue":0,"caExpDate":"11-Jul-2023","ca":"ANNUAL GENERAL MEETING/DIVIDEND - RS 12 PER SHARE/ SPECIAL DIVIDEND - RS 10 PER SHARE 11-Jul-2023","meta":{"isSLBSec":true}},{"symbol":"AUBANK","buyOrderPrice1":6.11,"buyOrderQty1":4577,"sellOrderPrice1":6.74,"sellQty1":582,"lastTradedPrice":6.75,"underLyingLtp":737.65,"futuresLtp":738.15,"spread":-0.5,"spreadPer":-0.07,"openPositions":0,"annualisedYieldPer":33.39998644343524,"volume":336541,"turnOver":2150496.99,"transactionValue":252843253.3,"caExpDate":"14-Jul-2023","ca":"DIVIDEND - RE 1 PER SHARE 14-Jul-2023","meta":{"isSLBSec":true}},{"symbol":"HINDCOPPER","buyOrderPrice1":0,"buyOrderQty1":0,"sellOrderPrice1":0.99,"sellQty1":1100,"lastTradedPrice":0,"underLyingLtp":158.15,"futuresLtp":158.3,"spread":-0.15,"spreadPer":-0.09,"openPositions":0,"annualisedYieldPer":0,"volume":0,"turnOver":0,"transactionValue":0,"caExpDate":"22-Sep-2023","ca":"ANNUAL GENERAL MEETING/DIVIDEND - RE 0.92 PER SHARE 22-Sep-2023","meta":{"isSLBSec":true}},{"symbol":"COFORGE","buyOrderPrice1":0,"buyOrderQty1":0,"sellOrderPrice1":79,"sellQty1":50,"lastTradedPrice":0,"underLyingLtp":5278.45,"futuresLtp":5283.1,"spread":-4.65,"spreadPer":-0.09,"openPositions":0,"annualisedYieldPer":34.57454366338603,"volume":0,"turnOver":0,"transactionValue":0,"caExpDate":"03-Aug-2023","ca":"INTERIM DIVIDEND - RS 19 PER SHARE 03-Aug-2023","meta":{"isSLBSec":true}},{"symbol":"CIPLA","buyOrderPrice1":0,"buyOrderQty1":0,"sellOrderPrice1":0.99,"sellQty1":464,"lastTradedPrice":0,"underLyingLtp":1180,"futuresLtp":1181.2,"spread":-1.2,"spreadPer":-0.1,"openPositions":0,"annualisedYieldPer":1.5466101694915255,"volume":0,"turnOver":0,"transactionValue":0,"caExpDate":"21-Jul-2023","ca":"DIVIDEND - RS 8.50 PER SHARE 21-Jul-2023","meta":{"isSLBSec":true}},{"symbol":"AARTIIND","buyOrderPrice1":0,"buyOrderQty1":0,"sellOrderPrice1":0.99,"sellQty1":882,"lastTradedPrice":0,"underLyingLtp":496.95,"futuresLtp":497.5,"spread":-0.55,"spreadPer":-0.11,"openPositions":0,"annualisedYieldPer":0,"volume":0,"turnOver":0,"transactionValue":0,"caExpDate":"28-Jul-2023","ca":"DIVIDEND - RS 1.50 PER SHARE 28-Jul-2023","meta":{"isSLBSec":true}},{"symbol":"CHOLAFIN","buyOrderPrice1":0,"buyOrderQty1":0,"sellOrderPrice1":4,"sellQty1":4250,"lastTradedPrice":0,"underLyingLtp":1187.15,"futuresLtp":1188.5,"spread":-1.35,"spreadPer":-0.11,"openPositions":0,"annualisedYieldPer":12.298361622372909,"volume":0,"turnOver":0,"transactionValue":0,"caExpDate":"25-Jul-2023","ca":"ANNUAL GENERAL MEETING/DIVIDEND - RE 0.70 PER SHARE 25-Jul-2023","meta":{"isSLBSec":true}},{"symbol":"VEDL","buyOrderPrice1":0,"buyOrderQty1":0,"sellOrderPrice1":2,"sellQty1":500,"lastTradedPrice":0,"underLyingLtp":224.15,"futuresLtp":224.4,"spread":-0.25,"spreadPer":-0.11,"openPositions":0,"annualisedYieldPer":4.070934641980816,"volume":0,"turnOver":0,"transactionValue":0,"caExpDate":"06-Jul-2023","ca":"ANNUAL GENERAL MEETING 06-Jul-2023","meta":{"isSLBSec":true}},{"symbol":"AMBUJACEM","buyOrderPrice1":0,"buyOrderQty1":0,"sellOrderPrice1":2,"sellQty1":280,"lastTradedPrice":0,"underLyingLtp":422.2,"futuresLtp":422.7,"spread":-0.5,"spreadPer":-0.12,"openPositions":0,"annualisedYieldPer":2.161297963050687,"volume":0,"turnOver":0,"transactionValue":0,"caExpDate":"07-Jul-2023","ca":"DIVIDEND - RS 2.50 PER SHARE 07-Jul-2023","meta":{"isSLBSec":true}},{"symbol":"PIDILITIND","buyOrderPrice1":0,"buyOrderQty1":0,"sellOrderPrice1":1.5,"sellQty1":47,"lastTradedPrice":0,"underLyingLtp":2495.45,"futuresLtp":2498.5,"spread":-3.05,"spreadPer":-0.12,"openPositions":0,"annualisedYieldPer":2.193993067382637,"volume":0,"turnOver":0,"transactionValue":0,"caExpDate":"27-Jul-2023","ca":"ANNUAL GENERAL MEETING 27-Jul-2023","meta":{"isSLBSec":true}},{"symbol":"ABCAPITAL","buyOrderPrice1":0,"buyOrderQty1":0,"sellOrderPrice1":0.99,"sellQty1":2366,"lastTradedPrice":0,"underLyingLtp":175.05,"futuresLtp":175.3,"spread":-0.25,"spreadPer":-0.14,"openPositions":0,"annualisedYieldPer":0,"volume":0,"turnOver":0,"transactionValue":0,"caExpDate":"16-Aug-2018","ca":" ANNUAL GENERAL MEETING 16-Aug-2018","meta":{"isSLBSec":true}},{"symbol":"GUJGASLTD","buyOrderPrice1":0,"buyOrderQty1":0,"sellOrderPrice1":1.9,"sellQty1":500,"lastTradedPrice":0,"underLyingLtp":439.5,"futuresLtp":440.1,"spread":-0.6,"spreadPer":-0.14,"openPositions":0,"annualisedYieldPer":99.65870307167236,"volume":0,"turnOver":0,"transactionValue":0,"caExpDate":"11-Sep-2023","ca":"DIVIDEND - RS 6.65 PER SHARE 11-Sep-2023","meta":{"isSLBSec":true}},{"symbol":"BHARTIARTL","buyOrderPrice1":0,"buyOrderQty1":0,"sellOrderPrice1":0.5,"sellQty1":1000,"lastTradedPrice":0,"underLyingLtp":908.4,"futuresLtp":909.9,"spread":-1.5,"spreadPer":-0.17,"openPositions":0,"annualisedYieldPer":11.853258476442097,"volume":0,"turnOver":0,"transactionValue":0,"caExpDate":"11-Aug-2023","ca":"DIVIDEND - RS 4 PER SHARE 11-Aug-2023","meta":{"isSLBSec":true}},{"symbol":"RBLBANK","buyOrderPrice1":0,"buyOrderQty1":0,"sellOrderPrice1":0.99,"sellQty1":300,"lastTradedPrice":0,"underLyingLtp":238.35,"futuresLtp":238.75,"spread":-0.4,"spreadPer":-0.17,"openPositions":0,"annualisedYieldPer":19.142018040696453,"volume":0,"turnOver":0,"transactionValue":0,"caExpDate":"18-Aug-2023","ca":"DIVIDEND - RS 1.50 PER SHARE 18-Aug-2023","meta":{"isSLBSec":true}},{"symbol":"RELIANCE","buyOrderPrice1":0,"buyOrderQty1":0,"sellOrderPrice1":0.5,"sellQty1":100,"lastTradedPrice":0,"underLyingLtp":2338.8,"futuresLtp":2343,"spread":-4.2,"spreadPer":-0.18,"openPositions":0,"annualisedYieldPer":1.560629382589362,"volume":0,"turnOver":0,"transactionValue":0,"caExpDate":"21-Aug-2023","ca":"DIVIDEND - RS 9 PER SHARE 21-Aug-2023","meta":{"isSLBSec":true}},{"symbol":"BIOCON","buyOrderPrice1":0,"buyOrderQty1":0,"sellOrderPrice1":0.99,"sellQty1":500,"lastTradedPrice":0,"underLyingLtp":263.7,"futuresLtp":264.25,"spread":-0.55,"spreadPer":-0.21,"openPositions":0,"annualisedYieldPer":0,"volume":0,"turnOver":0,"transactionValue":0,"caExpDate":"07-Jul-2023","ca":"DIVIDEND - RS 1.50 PER SHARE 07-Jul-2023","meta":{"isSLBSec":true}},{"symbol":"MARICO","buyOrderPrice1":0,"buyOrderQty1":0,"sellOrderPrice1":0.99,"sellQty1":4000,"lastTradedPrice":0,"underLyingLtp":578.2,"futuresLtp":579.5,"spread":-1.3,"spreadPer":-0.22,"openPositions":0,"annualisedYieldPer":0,"volume":0,"turnOver":0,"transactionValue":0,"caExpDate":"08-Mar-2023","ca":"INTERIM DIVIDEND - RS 4.50 PER SHARE 08-Mar-2023","meta":{"isSLBSec":true}},{"symbol":"HDFCBANK","buyOrderPrice1":0,"buyOrderQty1":0,"sellOrderPrice1":0.49,"sellQty1":3733,"lastTradedPrice":0,"underLyingLtp":1528,"futuresLtp":1531.35,"spread":-3.35,"spreadPer":-0.22,"openPositions":0,"annualisedYieldPer":1.1943717277486912,"volume":0,"turnOver":0,"transactionValue":0,"caExpDate":"16-May-2023","ca":"DIVIDEND - RS 19 PER SHARE 16-May-2023","meta":{"isSLBSec":true}},{"symbol":"HAL","buyOrderPrice1":0,"buyOrderQty1":0,"sellOrderPrice1":29,"sellQty1":75,"lastTradedPrice":0,"underLyingLtp":3840.2,"futuresLtp":3848.9,"spread":-8.7,"spreadPer":-0.23,"openPositions":0,"annualisedYieldPer":0,"volume":0,"turnOver":0,"transactionValue":0,"caExpDate":"29-Sep-2023","ca":"FACE VALUE SPLIT (SUB-DIVISION) - FROM RS 10/- PER SHARE TO RS 5/- PER SHARE 29-Sep-2023","meta":{"isSLBSec":true}},{"symbol":"MPHASIS","buyOrderPrice1":0.5,"buyOrderQty1":5000,"sellOrderPrice1":5,"sellQty1":4108,"lastTradedPrice":0,"underLyingLtp":2482.2,"futuresLtp":2487.95,"spread":-5.75,"spreadPer":-0.23,"openPositions":0,"annualisedYieldPer":0,"volume":0,"turnOver":0,"transactionValue":0,"caExpDate":"05-Jul-2023","ca":"ANNUAL GENERAL MEETING/DIVIDEND - RS 50 PER SHARE 05-Jul-2023","meta":{"isSLBSec":true}},{"symbol":"ESCORTS","buyOrderPrice1":0,"buyOrderQty1":0,"sellOrderPrice1":9.9,"sellQty1":100,"lastTradedPrice":0,"underLyingLtp":3224.25,"futuresLtp":3232.7,"spread":-8.45,"spreadPer":-0.26,"openPositions":0,"annualisedYieldPer":10.1884159106769,"volume":0,"turnOver":0,"transactionValue":0,"caExpDate":"30-Jun-2023","ca":"ANNUAL GENERAL MEETING/DIVIDEND - RS 7 PER SHARE 30-Jun-2023","meta":{"isSLBSec":true}},{"symbol":"PEL","buyOrderPrice1":0,"buyOrderQty1":0,"sellOrderPrice1":25,"sellQty1":198,"lastTradedPrice":0,"underLyingLtp":1057.2,"futuresLtp":1060.1,"spread":-2.9,"spreadPer":-0.27,"openPositions":0,"annualisedYieldPer":6.90503216042376,"volume":0,"turnOver":0,"transactionValue":0,"caExpDate":"25-Aug-2023","ca":"BUY BACK 25-Aug-2023","meta":{"isSLBSec":true}},{"symbol":"ABB","buyOrderPrice1":0,"buyOrderQty1":0,"sellOrderPrice1":25,"sellQty1":396,"lastTradedPrice":0,"underLyingLtp":4162.05,"futuresLtp":4173.6,"spread":-11.55,"spreadPer":-0.28,"openPositions":0,"annualisedYieldPer":0.8769716846265662,"volume":0,"turnOver":0,"transactionValue":0,"caExpDate":"25-Aug-2023","ca":"SPECIAL DIVIDEND - RS  5.50 PER SHARE 25-Aug-2023","meta":{"isSLBSec":true}},{"symbol":"BHEL","buyOrderPrice1":0,"buyOrderQty1":0,"sellOrderPrice1":0.5,"sellQty1":300,"lastTradedPrice":0,"underLyingLtp":124.85,"futuresLtp":125.2,"spread":-0.35,"spreadPer":-0.28,"openPositions":0,"annualisedYieldPer":4.385262314777734,"volume":0,"turnOver":0,"transactionValue":0,"caExpDate":"11-Aug-2023","ca":"DIVIDEND - RE 0.40 PER SHARE 11-Aug-2023","meta":{"isSLBSec":true}},{"symbol":"RECLTD","buyOrderPrice1":0,"buyOrderQty1":0,"sellOrderPrice1":1,"sellQty1":2300,"lastTradedPrice":0,"underLyingLtp":270.65,"futuresLtp":271.5,"spread":-0.85,"spreadPer":-0.31,"openPositions":0,"annualisedYieldPer":0,"volume":0,"turnOver":0,"transactionValue":0,"caExpDate":"14-Aug-2023","ca":"INTERIM DIVIDEND - RS 3 PER SHARE 14-Aug-2023","meta":{"isSLBSec":true}},{"symbol":"ASTRAL","buyOrderPrice1":1,"buyOrderQty1":5000,"sellOrderPrice1":10,"sellQty1":80,"lastTradedPrice":0,"underLyingLtp":1840,"futuresLtp":1845.65,"spread":-5.65,"spreadPer":-0.31,"openPositions":0,"annualisedYieldPer":29.7554347826087,"volume":0,"turnOver":0,"transactionValue":0,"caExpDate":"04-Aug-2023","ca":"DIVIDEND - RS 2.25 PER SHARE 04-Aug-2023","meta":{"isSLBSec":true}},{"symbol":"VOLTAS","buyOrderPrice1":0,"buyOrderQty1":0,"sellOrderPrice1":5,"sellQty1":437,"lastTradedPrice":0,"underLyingLtp":867.15,"futuresLtp":870,"spread":-2.85,"spreadPer":-0.33,"openPositions":0,"annualisedYieldPer":8.460473966441791,"volume":0,"turnOver":0,"transactionValue":0,"caExpDate":"09-Jun-2023","ca":"ANNUAL GENERAL MEETING/DIVIDEND - RS 4.25 PER SHARE 09-Jun-2023","meta":{"isSLBSec":true}},{"symbol":"POWERGRID","buyOrderPrice1":0,"buyOrderQty1":0,"sellOrderPrice1":0.99,"sellQty1":515,"lastTradedPrice":0,"underLyingLtp":199.2,"futuresLtp":199.85,"spread":-0.65,"spreadPer":-0.33,"openPositions":0,"annualisedYieldPer":10.993975903614459,"volume":0,"turnOver":0,"transactionValue":0,"caExpDate":"12-Sep-2023","ca":"BONUS 1:3 12-Sep-2023","meta":{"isSLBSec":true}},{"symbol":"SHREECEM","buyOrderPrice1":0,"buyOrderQty1":0,"sellOrderPrice1":99,"sellQty1":10,"lastTradedPrice":0,"underLyingLtp":25801,"futuresLtp":25928.05,"spread":-127.05,"spreadPer":-0.49,"openPositions":0,"annualisedYieldPer":41.025541645672654,"volume":0,"turnOver":0,"transactionValue":0,"caExpDate":"01-Jun-2023","ca":"INTERIM DIVIDEND - RS 55 PER SHARE 01-Jun-2023","meta":{"isSLBSec":true}}],"timestamp":"25-Sep-2023 14:14:26","meta":"Oct-2023(O1)**","marketStatus":{"market":"SLBS","marketOpenOrClose":"Open","marketCurrentTradingDate":"Sep 25,2023","marketOpenTime":"0915","marketCloseTime":"1700","marketPreviousTradingDate":"Sep 22,2023","marketNextTradingDate":"Sep 26,2023","marketStatusMessage":"Market is Open"}}